verilog/downsample.v
module downsample_verilog(
    input data_in_valid,
    input [15:0] data_in_data,
    output data_in_ready,
    output data_out_valid,
    output [15:0] data_out_data,
    input data_out_ready,
    input CLK
);
reg [4:0] x;
reg [4:0] y;
reg [4:0] x_next;
reg [4:0] y_next;

wire keep;

assign keep = (x % 2 == 0) & (y % 2 == 0);
assign data_out_valid = keep & data_in_valid;
assign data_in_ready = data_out_ready | ~keep;
assign data_out_data = data_in_data;

always @(*) begin
    if (data_in_valid & data_out_ready) begin
        x_next = x + 1;
        if (x == 31) begin
            y_next = y + 1;
        end else begin
            y_next = y;
        end
    end else begin
        x_next = x;
        y_next = y;
    end
end


always @(posedge CLK) begin
    x <= x_next;
    y <= y_next;
end
endmodule

build/logs/downsample_verilog.vcd
$version Generated by VerilatedVcd $end
$date Thu Sep 26 09:49:12 2019
 $end
$timescale   1ns $end

 $scope module TOP $end
  $var wire  1 . CLK $end
  $var wire 16 ) data_in_data [15:0] $end
  $var wire  1 * data_in_ready $end
  $var wire  1 ( data_in_valid $end
  $var wire 16 , data_out_data [15:0] $end
  $var wire  1 - data_out_ready $end
  $var wire  1 + data_out_valid $end
  $scope module downsample_verilog $end
   $var wire  1 . CLK $end
   $var wire 16 ) data_in_data [15:0] $end
   $var wire  1 * data_in_ready $end
   $var wire  1 ( data_in_valid $end
   $var wire 16 , data_out_data [15:0] $end
   $var wire  1 - data_out_ready $end
   $var wire  1 + data_out_valid $end
   $var wire  1 % keep $end
   $var wire  5 & x [4:0] $end
   $var wire  5 # x_next [4:0] $end
   $var wire  5 ' y [4:0] $end
   $var wire  5 $ y_next [4:0] $end
  $upscope $end
 $upscope $end
$enddefinitions $end


#1
b00000 #
b00000 $
1%
b00000 &
b00000 '
0(
b0000000000000000 )
0*
0+
b0000000000000000 ,
0-
1.
#2
0.
#3
1*
1-
#4
1.
#5
0.
#6
1(
0*
1+
0-
#7
1.
#8
0.
#9
0(
0+
#10
1.
#11
0.
#12
1*
1-
#13
1.
#14
0.
#15
1(
0*
1+
0-
#16
1.
#17
0.
#18
0(
0+
#19
1.
#20
0.
#21
#22
1.
#23
0.
#24
b00001 #
1(
1*
1+
1-
#25
b00010 #
0%
b00001 &
0+
1.
#26
0.
#27
b0000000000000001 )
b0000000000000001 ,
0-
#28
1%
b00010 &
0*
1+
1.
#29
0.
#30
b0000000000000010 )
b0000000000000010 ,
#31
1.
#32
0.
#33
0(
0+
#34
1.
#35
0.
#36
1(
1+
#37
1.
#38
0.
#39
b00011 #
1*
1-
#40
b00100 #
0%
b00011 &
0+
1.
#41
0.
#42
b0000000000000011 )
b0000000000000011 ,
#43
b00101 #
1%
b00100 &
1+
1.
#44
0.
#45
b00100 #
b0000000000000100 )
0*
b0000000000000100 ,
0-
#46
1.
#47
0.
#48
0(
0+
#49
1.
#50
0.
#51
1*
1-
#52
1.
#53
0.
#54
b00101 #
1(
1+
#55
b00110 #
0%
b00101 &
0+
1.
#56
0.
#57
b0000000000000101 )
b0000000000000101 ,
#58
b00111 #
1%
b00110 &
1+
1.
#59
0.
#60
b00110 #
0(
b0000000000000110 )
0+
b0000000000000110 ,
#61
1.
#62
0.
#63
0*
0-
#64
1.
#65
0.
#66
1*
1-
#67
1.
#68
0.
#69
#70
1.
#71
0.
#72
#73
1.
#74
0.
#75
#76
1.
#77
0.
#78
1(
0*
1+
0-
#79
1.
#80
0.
#81
b00111 #
1*
1-
#82
b01000 #
0%
b00111 &
0+
1.
#83
0.
#84
b0000000000000111 )
b0000000000000111 ,
0-
#85
1%
b01000 &
0*
1+
1.
#86
0.
#87
b01001 #
b0000000000001000 )
1*
b0000000000001000 ,
1-
#88
b01010 #
0%
b01001 &
0+
1.
#89
0.
#90
b01001 #
0(
b0000000000001001 )
b0000000000001001 ,
#91
1.
#92
0.
#93
b01010 #
1(
#94
b01011 #
1%
b01010 &
1+
1.
#95
0.
#96
b0000000000001010 )
b0000000000001010 ,
#97
b01100 #
0%
b01011 &
0+
1.
#98
0.
#99
b0000000000001011 )
b0000000000001011 ,
0-
#100
1%
b01100 &
0*
1+
1.
#101
0.
#102
0(
b0000000000001100 )
0+
b0000000000001100 ,
#103
1.
#104
0.
#105
b01101 #
1(
1*
1+
1-
#106
b01110 #
0%
b01101 &
0+
1.
#107
0.
#108
b01101 #
0(
b0000000000001101 )
b0000000000001101 ,
#109
1.
#110
0.
#111
b01110 #
1(
0-
#112
1%
b01110 &
0*
1+
1.
#113
0.
#114
0(
b0000000000001110 )
0+
b0000000000001110 ,
#115
1.
#116
0.
#117
b01111 #
1(
1*
1+
1-
#118
b10000 #
0%
b01111 &
0+
1.
#119
0.
#120
b01111 #
0(
b0000000000001111 )
b0000000000001111 ,
#121
1.
#122
0.
#123
b10000 #
1(
0-
#124
1%
b10000 &
0*
1+
1.
#125
0.
#126
0(
b0000000000010000 )
0+
b0000000000010000 ,
#127
1.
#128
0.
#129
#130
1.
#131
0.
#132
1(
1+
#133
1.
#134
0.
#135
#136
1.
#137
0.
#138
0(
1*
0+
1-
#139
1.
#140
0.
#141
0*
0-
#142
1.
#143
0.
#144
1*
1-
#145
1.
#146
0.
#147
#148
1.
#149
0.
#150
#151
1.
#152
0.
#153
1(
0*
1+
0-
#154
1.
#155
0.
#156
0(
0+
#157
1.
#158
0.
#159
b10001 #
1(
1*
1+
1-
#160
b10010 #
0%
b10001 &
0+
1.
#161
0.
#162
b10001 #
0(
b0000000000010001 )
b0000000000010001 ,
#163
1.
#164
0.
#165
#166
1.
#167
0.
#168
b10010 #
1(
0-
#169
1%
b10010 &
0*
1+
1.
#170
0.
#171
0(
b0000000000010010 )
0+
b0000000000010010 ,
#172
1.
#173
0.
#174
#175
1.
#176
0.
#177
1*
1-
#178
1.
#179
0.
#180
1(
0*
1+
0-
#181
1.
#182
0.
#183
0(
1*
0+
1-
#184
1.
#185
0.
#186
1(
0*
1+
0-
#187
1.
#188
0.
#189
b10011 #
1*
1-
#190
b10100 #
0%
b10011 &
0+
1.
#191
0.
#192
b0000000000010011 )
b0000000000010011 ,
#193
b10101 #
1%
b10100 &
1+
1.
#194
0.
#195
b0000000000010100 )
b0000000000010100 ,
#196
b10110 #
0%
b10101 &
0+
1.
#197
0.
#198
b10101 #
0(
b0000000000010101 )
b0000000000010101 ,
0-
#199
1.
#200
0.
#201
b10110 #
1(
#202
1%
b10110 &
0*
1+
1.
#203
0.
#204
0(
b0000000000010110 )
1*
0+
b0000000000010110 ,
1-
#205
1.
#206
0.
#207
b10111 #
1(
1+
#208
b11000 #
0%
b10111 &
0+
1.
#209
0.
#210
b0000000000010111 )
b0000000000010111 ,
#211
b11001 #
1%
b11000 &
1+
1.
#212
0.
#213
b0000000000011000 )
b0000000000011000 ,
#214
b11010 #
0%
b11001 &
0+
1.
#215
0.
#216
b0000000000011001 )
b0000000000011001 ,
0-
#217
1%
b11010 &
0*
1+
1.
#218
0.
#219
b11011 #
b0000000000011010 )
1*
b0000000000011010 ,
1-
#220
b11100 #
0%
b11011 &
0+
1.
#221
0.
#222
b0000000000011011 )
b0000000000011011 ,
0-
#223
1%
b11100 &
0*
1+
1.
#224
0.
#225
b0000000000011100 )
b0000000000011100 ,
#226
1.
#227
0.
#228
0(
1*
0+
1-
#229
1.
#230
0.
#231
0*
0-
#232
1.
#233
0.
#234
b11101 #
1(
1*
1+
1-
#235
b11110 #
0%
b11101 &
0+
1.
#236
0.
#237
b0000000000011101 )
b0000000000011101 ,
#238
b11111 #
1%
b11110 &
1+
1.
#239
0.
#240
b11110 #
0(
b0000000000011110 )
0*
0+
b0000000000011110 ,
0-
#241
1.
#242
0.
#243
b11111 #
1(
1*
1+
1-
#244
b00000 #
b00001 $
0%
b11111 &
0+
1.
#245
0.
#246
b0000000000011111 )
b0000000000011111 ,
0-
#247
b00001 #
b00000 &
b00001 '
1.
#248
0.
#249
b00000 #
0(
b0000000000100000 )
b0000000000100000 ,
1-
#250
1.
#251
0.
#252
0-
#253
1.
#254
0.
#255
#256
1.
#257
0.
#258
#259
1.
#260
0.
#261
b00001 #
1(
1-
#262
b00010 #
b00001 &
1.
#263
0.
#264
b0000000000100001 )
b0000000000100001 ,
0-
#265
b00011 #
b00010 &
1.
#266
0.
#267
b0000000000100010 )
b0000000000100010 ,
1-
#268
b00100 #
b00011 &
1.
#269
0.
#270
b00011 #
0(
b0000000000100011 )
b0000000000100011 ,
0-
#271
1.
#272
0.
#273
b00100 #
1(
1-
#274
b00101 #
b00100 &
1.
#275
0.
#276
b00100 #
0(
b0000000000100100 )
b0000000000100100 ,
0-
#277
1.
#278
0.
#279
#280
1.
#281
0.
#282
b00101 #
1(
1-
#283
b00110 #
b00101 &
1.
#284
0.
#285
b0000000000100101 )
b0000000000100101 ,
#286
b00111 #
b00110 &
1.
#287
0.
#288
b00110 #
0(
b0000000000100110 )
b0000000000100110 ,
#289
1.
#290
0.
#291
#292
1.
#293
0.
#294
b00111 #
1(
0-
#295
b01000 #
b00111 &
1.
#296
0.
#297
b0000000000100111 )
b0000000000100111 ,
#298
b01001 #
b01000 &
1.
#299
0.
#300
b0000000000101000 )
b0000000000101000 ,
1-
#301
b01010 #
b01001 &
1.
#302
0.
#303
b01001 #
0(
b0000000000101001 )
b0000000000101001 ,
#304
1.
#305
0.
#306
#307
1.
#308
0.
#309
b01010 #
1(
#310
b01011 #
b01010 &
1.
#311
0.
#312
b01010 #
0(
b0000000000101010 )
b0000000000101010 ,
0-
#313
1.
#314
0.
#315
b01011 #
1(
#316
b01100 #
b01011 &
1.
#317
0.
#318
b01011 #
0(
b0000000000101011 )
b0000000000101011 ,
1-
#319
1.
#320
0.
#321
#322
1.
#323
0.
#324
b01100 #
1(
#325
b01101 #
b01100 &
1.
#326
0.
#327
b01100 #
0(
b0000000000101100 )
b0000000000101100 ,
0-
#328
1.
#329
0.
#330
#331
1.
#332
0.
#333
1-
#334
1.
#335
0.
#336
#337
1.
#338
0.
#339
0-
#340
1.
#341
0.
#342
b01101 #
1(
1-
#343
b01110 #
b01101 &
1.
#344
0.
#345
b01101 #
0(
b0000000000101101 )
b0000000000101101 ,
#346
1.
#347
0.
#348
b01110 #
1(
#349
b01111 #
b01110 &
1.
#350
0.
#351
b0000000000101110 )
b0000000000101110 ,
#352
b10000 #
b01111 &
1.
#353
0.
#354
b0000000000101111 )
b0000000000101111 ,
#355
b10001 #
b10000 &
1.
#356
0.
#357
b10000 #
0(
b0000000000110000 )
b0000000000110000 ,
#358
1.
#359
0.
#360
b10001 #
1(
0-
#361
b10010 #
b10001 &
1.
#362
0.
#363
b10001 #
0(
b0000000000110001 )
b0000000000110001 ,
1-
#364
1.
#365
0.
#366
#367
1.
#368
0.
#369
b10010 #
1(
#370
b10011 #
b10010 &
1.
#371
0.
#372
b0000000000110010 )
b0000000000110010 ,
#373
b10100 #
b10011 &
1.
#374
0.
#375
b0000000000110011 )
b0000000000110011 ,
0-
#376
b10101 #
b10100 &
1.
#377
0.
#378
b10100 #
0(
b0000000000110100 )
b0000000000110100 ,
1-
#379
1.
#380
0.
#381
b10101 #
1(
0-
#382
b10110 #
b10101 &
1.
#383
0.
#384
b10101 #
0(
b0000000000110101 )
b0000000000110101 ,
1-
#385
1.
#386
0.
#387
#388
1.
#389
0.
#390
b10110 #
1(
#391
b10111 #
b10110 &
1.
#392
0.
#393
b10110 #
0(
b0000000000110110 )
b0000000000110110 ,
0-
#394
1.
#395
0.
#396
b10111 #
1(
#397
b11000 #
b10111 &
1.
#398
0.
#399
b10111 #
0(
b0000000000110111 )
b0000000000110111 ,
#400
1.
#401
0.
#402
b11000 #
1(
#403
b11001 #
b11000 &
1.
#404
0.
#405
b0000000000111000 )
b0000000000111000 ,
1-
#406
b11010 #
b11001 &
1.
#407
0.
#408
b11001 #
0(
b0000000000111001 )
b0000000000111001 ,
#409
1.
#410
0.
#411
b11010 #
1(
0-
#412
b11011 #
b11010 &
1.
#413
0.
#414
b11010 #
0(
b0000000000111010 )
b0000000000111010 ,
#415
1.
#416
0.
#417
1-
#418
1.
#419
0.
#420
b11011 #
1(
0-
#421
b11100 #
b11011 &
1.
#422
0.
#423
b0000000000111011 )
b0000000000111011 ,
#424
b11101 #
b11100 &
1.
#425
0.
#426
b11100 #
0(
b0000000000111100 )
b0000000000111100 ,
#427
1.
#428
0.
#429
1-
#430
1.
#431
0.
#432
#433
1.
#434
0.
#435
b11101 #
1(
0-
#436
b11110 #
b11101 &
1.
#437
0.
#438
b11101 #
0(
b0000000000111101 )
b0000000000111101 ,
#439
1.
#440
0.
#441
1-
#442
1.
#443
0.
#444
b11110 #
1(
#445
b11111 #
b11110 &
1.
#446
0.
#447
b0000000000111110 )
b0000000000111110 ,
0-
#448
b00000 #
b00010 $
b11111 &
1.
#449
0.
#450
b11111 #
b00001 $
0(
b0000000000111111 )
b0000000000111111 ,
#451
1.
#452
0.
#453
1-
#454
1.
#455
0.
#456
0-
#457
1.
#458
0.
#459
#460
1.
#461
0.
#462
#463
1.
#464
0.
#465
b00000 #
b00010 $
1(
#466
1%
b00000 &
b00010 '
0*
1+
1.
#467
0.
#468
0(
b0000000001000000 )
0+
b0000000001000000 ,
#469
1.
#470
0.
#471
1(
1+
#472
1.
#473
0.
#474
#475
1.
#476
0.
#477
b00001 #
1*
1-
#478
b00010 #
0%
b00001 &
0+
1.
#479
0.
#480
b00001 #
0(
b0000000001000001 )
b0000000001000001 ,
#481
1.
#482
0.
#483
0-
#484
1.
#485
0.
#486
b00010 #
1(
1-
#487
b00011 #
1%
b00010 &
1+
1.
#488
0.
#489
b00010 #
b0000000001000010 )
0*
b0000000001000010 ,
0-
#490
1.
#491
0.
#492
0(
1*
0+
1-
#493
1.
#494
0.
#495
1(
0*
1+
0-
#496
1.
#497
0.
#498
b00011 #
1*
1-
#499
b00100 #
0%
b00011 &
0+
1.
#500
0.
#501
b00011 #
0(
b0000000001000011 )
b0000000001000011 ,
#502
1.
#503
0.
#504
0-
#505
1.
#506
0.
#507
b00100 #
1(
#508
1%
b00100 &
0*
1+
1.
#509
0.
#510
0(
b0000000001000100 )
1*
0+
b0000000001000100 ,
1-
#511
1.
#512
0.
#513
0*
0-
#514
1.
#515
0.
#516
1(
1+
#517
1.
#518
0.
#519
b00101 #
1*
1-
#520
b00110 #
0%
b00101 &
0+
1.
#521
0.
#522
b00101 #
0(
b0000000001000101 )
b0000000001000101 ,
0-
#523
1.
#524
0.
#525
1-
#526
1.
#527
0.
#528
b00110 #
1(
#529
b00111 #
1%
b00110 &
1+
1.
#530
0.
#531
b00110 #
b0000000001000110 )
0*
b0000000001000110 ,
0-
#532
1.
#533
0.
#534
0(
0+
#535
1.
#536
0.
#537
1*
1-
#538
1.
#539
0.
#540
#541
1.
#542
0.
#543
#544
1.
#545
0.
#546
0*
0-
#547
1.
#548
0.
#549
1*
1-
#550
1.
#551
0.
#552
#553
1.
#554
0.
#555
1(
0*
1+
0-
#556
1.
#557
0.
#558
0(
1*
0+
1-
#559
1.
#560
0.
#561
#562
1.
#563
0.
#564
1(
0*
1+
0-
#565
1.
#566
0.
#567
0(
0+
#568
1.
#569
0.
#570
1(
1+
#571
1.
#572
0.
#573
0(
0+
#574
1.
#575
0.
#576
b00111 #
1(
1*
1+
1-
#577
b01000 #
0%
b00111 &
0+
1.
#578
0.
#579
b00111 #
0(
b0000000001000111 )
b0000000001000111 ,
0-
#580
1.
#581
0.
#582
b01000 #
1(
1-
#583
b01001 #
1%
b01000 &
1+
1.
#584
0.
#585
b01000 #
b0000000001001000 )
0*
b0000000001001000 ,
0-
#586
1.
#587
0.
#588
0(
0+
#589
1.
#590
0.
#591
1*
1-
#592
1.
#593
0.
#594
1(
0*
1+
0-
#595
1.
#596
0.
#597
b01001 #
1*
1-
#598
b01010 #
0%
b01001 &
0+
1.
#599
0.
#600
b01001 #
0(
b0000000001001001 )
b0000000001001001 ,
0-
#601
1.
#602
0.
#603
#604
1.
#605
0.
#606
1-
#607
1.
#608
0.
#609
0-
#610
1.
#611
0.
#612
b01010 #
1(
#613
1%
b01010 &
0*
1+
1.
#614
0.
#615
0(
b0000000001001010 )
0+
b0000000001001010 ,
#616
1.
#617
0.
#618
1(
1+
#619
1.
#620
0.
#621
0(
1*
0+
1-
#622
1.
#623
0.
#624
#625
1.
#626
0.
#627
#628
1.
#629
0.
#630
1(
0*
1+
0-
#631
1.
#632
0.
#633
0(
1*
0+
1-
#634
1.
#635
0.
#636
0*
0-
#637
1.
#638
0.
#639
1*
1-
#640
1.
#641
0.
#642
#643
1.
#644
0.
#645
b01011 #
1(
1+
#646
b01100 #
0%
b01011 &
0+
1.
#647
0.
#648
b0000000001001011 )
b0000000001001011 ,
0-
#649
1%
b01100 &
0*
1+
1.
#650
0.
#651
0(
b0000000001001100 )
1*
0+
b0000000001001100 ,
1-
#652
1.
#653
0.
#654
0*
0-
#655
1.
#656
0.
#657
b01101 #
1(
1*
1+
1-
#658
b01110 #
0%
b01101 &
0+
1.
#659
0.
#660
b01101 #
0(
b0000000001001101 )
b0000000001001101 ,
#661
1.
#662
0.
#663
b01110 #
1(
#664
b01111 #
1%
b01110 &
1+
1.
#665
0.
#666
b01110 #
b0000000001001110 )
0*
b0000000001001110 ,
0-
#667
1.
#668
0.
#669
#670
1.
#671
0.
#672
b01111 #
1*
1-
#673
b10000 #
0%
b01111 &
0+
1.
#674
0.
#675
b01111 #
0(
b0000000001001111 )
b0000000001001111 ,
#676
1.
#677
0.
#678
b10000 #
1(
#679
b10001 #
1%
b10000 &
1+
1.
#680
0.
#681
b10000 #
0(
b0000000001010000 )
0+
b0000000001010000 ,
#682
1.
#683
0.
#684
0*
0-
#685
1.
#686
0.
#687
b10001 #
1(
1*
1+
1-
#688
b10010 #
0%
b10001 &
0+
1.
#689
0.
#690
b10001 #
0(
b0000000001010001 )
b0000000001010001 ,
0-
#691
1.
#692
0.
#693
1-
#694
1.
#695
0.
#696
#697
1.
#698
0.
#699
#700
1.
#701
0.
#702
#703
1.
#704
0.
#705
#706
1.
#707
0.
#708
b10010 #
1(
0-
#709
1%
b10010 &
0*
1+
1.
#710
0.
#711
0(
b0000000001010010 )
1*
0+
b0000000001010010 ,
1-
#712
1.
#713
0.
#714
0*
0-
#715
1.
#716
0.
#717
b10011 #
1(
1*
1+
1-
#718
b10100 #
0%
b10011 &
0+
1.
#719
0.
#720
b10011 #
0(
b0000000001010011 )
b0000000001010011 ,
#721
1.
#722
0.
#723
b10100 #
1(
0-
#724
1%
b10100 &
0*
1+
1.
#725
0.
#726
b0000000001010100 )
b0000000001010100 ,
#727
1.
#728
0.
#729
#730
1.
#731
0.
#732
#733
1.
#734
0.
#735
b10101 #
1*
1-
#736
b10110 #
0%
b10101 &
0+
1.
#737
0.
#738
b10101 #
0(
b0000000001010101 )
b0000000001010101 ,
0-
#739
1.
#740
0.
#741
b10110 #
1(
1-
#742
b10111 #
1%
b10110 &
1+
1.
#743
0.
#744
b10110 #
0(
b0000000001010110 )
0+
b0000000001010110 ,
#745
1.
#746
0.
#747
#748
1.
#749
0.
#750
1(
0*
1+
0-
#751
1.
#752
0.
#753
b10111 #
1*
1-
#754
b11000 #
0%
b10111 &
0+
1.
#755
0.
#756
b10111 #
0(
b0000000001010111 )
b0000000001010111 ,
0-
#757
1.
#758
0.
#759
1-
#760
1.
#761
0.
#762
b11000 #
1(
#763
b11001 #
1%
b11000 &
1+
1.
#764
0.
#765
b11000 #
b0000000001011000 )
0*
b0000000001011000 ,
0-
#766
1.
#767
0.
#768
#769
1.
#770
0.
#771
b11001 #
1*
1-
#772
b11010 #
0%
b11001 &
0+
1.
#773
0.
#774
b11001 #
0(
b0000000001011001 )
b0000000001011001 ,
#775
1.
#776
0.
#777
#778
1.
#779
0.
#780
0-
#781
1.
#782
0.
#783
b11010 #
1(
1-
#784
b11011 #
1%
b11010 &
1+
1.
#785
0.
#786
b0000000001011010 )
b0000000001011010 ,
#787
b11100 #
0%
b11011 &
0+
1.
#788
0.
#789
b11011 #
0(
b0000000001011011 )
b0000000001011011 ,
#790
1.
#791
0.
#792
#793
1.
#794
0.
#795
b11100 #
1(
0-
#796
1%
b11100 &
0*
1+
1.
#797
0.
#798
0(
b0000000001011100 )
0+
b0000000001011100 ,
#799
1.
#800
0.
#801
#802
1.
#803
0.
#804
#805
1.
#806
0.
#807
1*
1-
#808
1.
#809
0.
#810
#811
1.
#812
0.
#813
#814
1.
#815
0.
#816
b11101 #
1(
1+
#817
b11110 #
0%
b11101 &
0+
1.
#818
0.
#819
b11101 #
0(
b0000000001011101 )
b0000000001011101 ,
0-
#820
1.
#821
0.
#822
b11110 #
1(
1-
#823
b11111 #
1%
b11110 &
1+
1.
#824
0.
#825
b0000000001011110 )
b0000000001011110 ,
#826
b00000 #
b00011 $
0%
b11111 &
0+
1.
#827
0.
#828
b11111 #
b00010 $
0(
b0000000001011111 )
b0000000001011111 ,
#829
1.
#830
0.
#831
b00000 #
b00011 $
1(
0-
#832
b00001 #
b00000 &
b00011 '
1.
#833
0.
#834
b0000000001100000 )
b0000000001100000 ,
#835
b00010 #
b00001 &
1.
#836
0.
#837
b0000000001100001 )
b0000000001100001 ,
1-
#838
b00011 #
b00010 &
1.
#839
0.
#840
b0000000001100010 )
b0000000001100010 ,
0-
#841
b00100 #
b00011 &
1.
#842
0.
#843
b00011 #
0(
b0000000001100011 )
b0000000001100011 ,
1-
#844
1.
#845
0.
#846
b00100 #
1(
#847
b00101 #
b00100 &
1.
#848
0.
#849
b0000000001100100 )
b0000000001100100 ,
0-
#850
b00110 #
b00101 &
1.
#851
0.
#852
b00101 #
0(
b0000000001100101 )
b0000000001100101 ,
#853
1.
#854
0.
#855
#856
1.
#857
0.
#858
b00110 #
1(
#859
b00111 #
b00110 &
1.
#860
0.
#861
b00110 #
0(
b0000000001100110 )
b0000000001100110 ,
1-
#862
1.
#863
0.
#864
b00111 #
1(
0-
#865
b01000 #
b00111 &
1.
#866
0.
#867
b00111 #
0(
b0000000001100111 )
b0000000001100111 ,
#868
1.
#869
0.
#870
b01000 #
1(
1-
#871
b01001 #
b01000 &
1.
#872
0.
#873
b01000 #
0(
b0000000001101000 )
b0000000001101000 ,
0-
#874
1.
#875
0.
#876
1-
#877
1.
#878
0.
#879
b01001 #
1(
#880
b01010 #
b01001 &
1.
#881
0.
#882
b01001 #
0(
b0000000001101001 )
b0000000001101001 ,
#883
1.
#884
0.
#885
#886
1.
#887
0.
#888
0-
#889
1.
#890
0.
#891
1-
#892
1.
#893
0.
#894
b01010 #
1(
#895
b01011 #
b01010 &
1.
#896
0.
#897
b01010 #
0(
b0000000001101010 )
b0000000001101010 ,
0-
#898
1.
#899
0.
#900
#901
1.
#902
0.
#903
b01011 #
1(
1-
#904
b01100 #
b01011 &
1.
#905
0.
#906
b01011 #
0(
b0000000001101011 )
b0000000001101011 ,
#907
1.
#908
0.
#909
#910
1.
#911
0.
#912
0-
#913
1.
#914
0.
#915
1-
#916
1.
#917
0.
#918
0-
#919
1.
#920
0.
#921
b01100 #
1(
1-
#922
b01101 #
b01100 &
1.
#923
0.
#924
b01100 #
0(
b0000000001101100 )
b0000000001101100 ,
0-
#925
1.
#926
0.
#927
b01101 #
1(
1-
#928
b01110 #
b01101 &
1.
#929
0.
#930
b0000000001101101 )
b0000000001101101 ,
#931
b01111 #
b01110 &
1.
#932
0.
#933
b0000000001101110 )
b0000000001101110 ,
#934
b10000 #
b01111 &
1.
#935
0.
#936
b01111 #
0(
b0000000001101111 )
b0000000001101111 ,
0-
#937
1.
#938
0.
#939
b10000 #
1(
1-
#940
b10001 #
b10000 &
1.
#941
0.
#942
b10000 #
0(
b0000000001110000 )
b0000000001110000 ,
0-
#943
1.
#944
0.
#945
#946
1.
#947
0.
#948
#949
1.
#950
0.
#951
1-
#952
1.
#953
0.
#954
b10001 #
1(
#955
b10010 #
b10001 &
1.
#956
0.
#957
b10001 #
0(
b0000000001110001 )
b0000000001110001 ,
0-
#958
1.
#959
0.
#960
b10010 #
1(
1-
#961
b10011 #
b10010 &
1.
#962
0.
#963
b0000000001110010 )
b0000000001110010 ,
#964
b10100 #
b10011 &
1.
#965
0.
#966
b10011 #
0(
b0000000001110011 )
b0000000001110011 ,
#967
1.
#968
0.
#969
b10100 #
1(
#970
b10101 #
b10100 &
1.
#971
0.
#972
b0000000001110100 )
b0000000001110100 ,
0-
#973
b10110 #
b10101 &
1.
#974
0.
#975
b10101 #
0(
b0000000001110101 )
b0000000001110101 ,
#976
1.
#977
0.
#978
#979
1.
#980
0.
#981
#982
1.
#983
0.
#984
b10110 #
1(
1-
#985
b10111 #
b10110 &
1.
#986
0.
#987
b10110 #
0(
b0000000001110110 )
b0000000001110110 ,
#988
1.
#989
0.
#990
b10111 #
1(
0-
#991
b11000 #
b10111 &
1.
#992
0.
#993
b10111 #
0(
b0000000001110111 )
b0000000001110111 ,
#994
1.
#995
0.
#996
1-
#997
1.
#998
0.
#999
b11000 #
1(
0-
#1000
b11001 #
b11000 &
1.
#1001
0.
#1002
b0000000001111000 )
b0000000001111000 ,
1-
#1003
b11010 #
b11001 &
1.
#1004
0.
#1005
b11001 #
0(
b0000000001111001 )
b0000000001111001 ,
0-
#1006
1.
#1007
0.
#1008
1-
#1009
1.
#1010
0.
#1011
#1012
1.
#1013
0.
#1014
0-
#1015
1.
#1016
0.
#1017
1-
#1018
1.
#1019
0.
#1020
b11010 #
1(
#1021
b11011 #
b11010 &
1.
#1022
0.
#1023
b0000000001111010 )
b0000000001111010 ,
0-
#1024
b11100 #
b11011 &
1.
#1025
0.
#1026
b0000000001111011 )
b0000000001111011 ,
#1027
b11101 #
b11100 &
1.
#1028
0.
#1029
b0000000001111100 )
b0000000001111100 ,
1-
#1030
b11110 #
b11101 &
1.
#1031
0.
#1032
b11101 #
0(
b0000000001111101 )
b0000000001111101 ,
#1033
1.
#1034
0.
#1035
b11110 #
1(
#1036
b11111 #
b11110 &
1.
#1037
0.
#1038
b11110 #
0(
b0000000001111110 )
b0000000001111110 ,
#1039
1.
#1040
0.
#1041
b11111 #
1(
0-
#1042
b00000 #
b00100 $
b11111 &
1.
#1043
0.
#1044
b0000000001111111 )
b0000000001111111 ,
#1045
1%
b00000 &
b00100 '
0*
1+
1.
#1046
0.
#1047
b0000000010000000 )
b0000000010000000 ,
#1048
1.
#1049
0.
#1050
0(
1*
0+
1-
#1051
1.
#1052
0.
#1053
1(
0*
1+
0-
#1054
1.
#1055
0.
#1056
0(
0+
#1057
1.
#1058
0.
#1059
b00001 #
1(
1*
1+
1-
#1060
b00010 #
0%
b00001 &
0+
1.
#1061
0.
#1062
b0000000010000001 )
b0000000010000001 ,
0-
#1063
1%
b00010 &
0*
1+
1.
#1064
0.
#1065
b00011 #
b0000000010000010 )
1*
b0000000010000010 ,
1-
#1066
b00100 #
0%
b00011 &
0+
1.
#1067
0.
#1068
b00011 #
0(
b0000000010000011 )
b0000000010000011 ,
#1069
1.
#1070
0.
#1071
0-
#1072
1.
#1073
0.
#1074
b00100 #
1(
1-
#1075
b00101 #
1%
b00100 &
1+
1.
#1076
0.
#1077
b00100 #
b0000000010000100 )
0*
b0000000010000100 ,
0-
#1078
1.
#1079
0.
#1080
#1081
1.
#1082
0.
#1083
#1084
1.
#1085
0.
#1086
#1087
1.
#1088
0.
#1089
#1090
1.
#1091
0.
#1092
#1093
1.
#1094
0.
#1095
#1096
1.
#1097
0.
#1098
0(
0+
#1099
1.
#1100
0.
#1101
1*
1-
#1102
1.
#1103
0.
#1104
b00101 #
1(
1+
#1105
b00110 #
0%
b00101 &
0+
1.
#1106
0.
#1107
b0000000010000101 )
b0000000010000101 ,
#1108
b00111 #
1%
b00110 &
1+
1.
#1109
0.
#1110
b00110 #
b0000000010000110 )
0*
b0000000010000110 ,
0-
#1111
1.
#1112
0.
#1113
b00111 #
1*
1-
#1114
b01000 #
0%
b00111 &
0+
1.
#1115
0.
#1116
b0000000010000111 )
b0000000010000111 ,
#1117
b01001 #
1%
b01000 &
1+
1.
#1118
0.
#1119
b01000 #
0(
b0000000010001000 )
0*
0+
b0000000010001000 ,
0-
#1120
1.
#1121
0.
#1122
1*
1-
#1123
1.
#1124
0.
#1125
b01001 #
1(
1+
#1126
b01010 #
0%
b01001 &
0+
1.
#1127
0.
#1128
b01001 #
0(
b0000000010001001 )
b0000000010001001 ,
#1129
1.
#1130
0.
#1131
#1132
1.
#1133
0.
#1134
b01010 #
1(
#1135
b01011 #
1%
b01010 &
1+
1.
#1136
0.
#1137
b01010 #
b0000000010001010 )
0*
b0000000010001010 ,
0-
#1138
1.
#1139
0.
#1140
b01011 #
1*
1-
#1141
b01100 #
0%
b01011 &
0+
1.
#1142
0.
#1143
b0000000010001011 )
b0000000010001011 ,
0-
#1144
1%
b01100 &
0*
1+
1.
#1145
0.
#1146
b0000000010001100 )
b0000000010001100 ,
#1147
1.
#1148
0.
#1149
b01101 #
1*
1-
#1150
b01110 #
0%
b01101 &
0+
1.
#1151
0.
#1152
b01101 #
0(
b0000000010001101 )
b0000000010001101 ,
0-
#1153
1.
#1154
0.
#1155
#1156
1.
#1157
0.
#1158
b01110 #
1(
1-
#1159
b01111 #
1%
b01110 &
1+
1.
#1160
0.
#1161
b01110 #
0(
b0000000010001110 )
0*
0+
b0000000010001110 ,
0-
#1162
1.
#1163
0.
#1164
b01111 #
1(
1*
1+
1-
#1165
b10000 #
0%
b01111 &
0+
1.
#1166
0.
#1167
b01111 #
0(
b0000000010001111 )
b0000000010001111 ,
0-
#1168
1.
#1169
0.
#1170
#1171
1.
#1172
0.
#1173
b10000 #
1(
#1174
1%
b10000 &
0*
1+
1.
#1175
0.
#1176
b10001 #
b0000000010010000 )
1*
b0000000010010000 ,
1-
#1177
b10010 #
0%
b10001 &
0+
1.
#1178
0.
