build/Downsample.v
module Downsample
(
  output [16-1:0] data_out_data,
  output data_in_ready,
  output data_out_valid,
  input data_in_valid,
  input [16-1:0] data_in_data,
  input data_out_ready,
  input CLK,
  input RESET
);

  reg keep;
  reg [5-1:0] y;
  reg [5-1:0] y_next;
  reg [5-1:0] x;
  reg [5-1:0] x_next;
  reg yield_state;
  reg yield_state_next;

  initial begin
    x = 0;
    y = 0;
  end


  always @(y or x or data_in_valid or data_in_data or data_out_ready or CLK or RESET or yield_state) begin
    x_next = x;
    y_next = y;
    if(yield_state == 0) begin
      if(y_next == 31) begin
        y_next = 0;
        x_next = 0;
        keep = (x_next % 2 == 0) & (y_next % 2 == 0);
        data_out_valid = keep & data_in_valid;
        data_out_data = data_in_data;
        data_in_ready = data_out_ready | ~keep;
        if(data_in_ready & data_in_valid) begin
          if(x_next == 31) begin
            yield_state_next = 0;
          end else begin
            x_next = x_next + 1;
            yield_state_next = 1;
          end
        end else begin
          yield_state_next = 1;
        end
      end else begin
        y_next = y_next + 1;
        x_next = 0;
        keep = (x_next % 2 == 0) & (y_next % 2 == 0);
        data_out_valid = keep & data_in_valid;
        data_out_data = data_in_data;
        data_in_ready = data_out_ready | ~keep;
        if(data_in_ready & data_in_valid) begin
          if(x_next == 31) begin
            yield_state_next = 0;
          end else begin
            x_next = x_next + 1;
            yield_state_next = 1;
          end
        end else begin
          yield_state_next = 1;
        end
      end
    end else begin
      keep = (x_next % 2 == 0) & (y_next % 2 == 0);
      data_out_valid = keep & data_in_valid;
      data_out_data = data_in_data;
      data_in_ready = data_out_ready | ~keep;
      if(data_in_ready & data_in_valid) begin
        if(x_next == 31) begin
          yield_state_next = 0;
        end else begin
          x_next = x_next + 1;
          yield_state_next = 1;
        end
      end else begin
        yield_state_next = 1;
      end
    end
  end


  always @(posedge CLK or posedge RESET) begin
    if(RESET) begin
      y_next = 0;
      x_next = 0;
      keep = (x_next % 2 == 0) & (y_next % 2 == 0);
      data_out_valid = keep & data_in_valid;
      data_out_data = data_in_data;
      data_in_ready = data_out_ready | ~keep;
      if(data_in_ready & data_in_valid) begin
        if(x_next == 31) begin
          yield_state_next = 0;
        end else begin
          x_next = x_next + 1;
          yield_state_next = 1;
        end
      end else begin
        yield_state_next = 1;
      end
      y <= y_next;
      x <= x_next;
      yield_state <= yield_state_next;
    end else begin
      y <= y_next;
      x <= x_next;
      yield_state <= yield_state_next;
    end
  end


endmodule

build/logs/Downsample.vcd
$version Generated by VerilatedVcd $end
$date Thu Dec  5 14:58:28 2019
 $end
$timescale   1ns $end

 $scope module TOP $end
  $var wire  1 0 CLK $end
  $var wire  1 1 RESET $end
  $var wire 16 . data_in_data [15:0] $end
  $var wire  1 + data_in_ready $end
  $var wire  1 - data_in_valid $end
  $var wire 16 * data_out_data [15:0] $end
  $var wire  1 / data_out_ready $end
  $var wire  1 , data_out_valid $end
  $scope module Downsample $end
   $var wire  1 0 CLK $end
   $var wire  1 1 RESET $end
   $var wire 16 . data_in_data [15:0] $end
   $var wire  1 + data_in_ready $end
   $var wire  1 - data_in_valid $end
   $var wire 16 * data_out_data [15:0] $end
   $var wire  1 / data_out_ready $end
   $var wire  1 , data_out_valid $end
   $var wire  1 % keep $end
   $var wire  5 $ x [4:0] $end
   $var wire  5 ' x_next [4:0] $end
   $var wire  5 # y [4:0] $end
   $var wire  5 & y_next [4:0] $end
   $var wire  1 ) yield_state $end
   $var wire  1 ( yield_state_next $end
  $upscope $end
 $upscope $end
$enddefinitions $end


#1
b00000 #
b00000 $
0%
b00001 &
b00000 '
1(
0)
b0000000000000000 *
1+
0,
0-
b0000000000000000 .
0/
00
01
#2
1%
b00000 &
1)
0+
11
#3
01
#4
b00001 '
1+
1,
1-
1/
#5
b00001 $
0%
b00010 '
0,
10
#6
00
#7
b00001 '
0-
0/
#8
b00010 '
b0000000000000001 *
1-
b0000000000000001 .
1/
#9
b00010 $
1%
b00011 '
1,
10
#10
00
#11
b00010 '
0+
0,
0-
0/
#12
b00011 '
b0000000000000010 *
1+
1,
1-
b0000000000000010 .
1/
#13
b00011 $
0%
b00100 '
0,
10
#14
00
#15
b00011 '
0-
0/
#16
b00100 '
b0000000000000011 *
1-
b0000000000000011 .
1/
#17
b00100 $
1%
b00101 '
1,
10
#18
00
#19
b00100 '
0+
0,
0-
0/
#20
b00101 '
b0000000000000100 *
1+
1,
1-
b0000000000000100 .
1/
#21
b00101 $
0%
b00110 '
0,
10
#22
00
#23
b00101 '
0-
0/
#24
b00110 '
b0000000000000101 *
1-
b0000000000000101 .
1/
#25
b00110 $
1%
b00111 '
1,
10
#26
00
#27
b00110 '
0+
0,
0-
0/
#28
b00111 '
b0000000000000110 *
1+
1,
1-
b0000000000000110 .
1/
#29
b00111 $
0%
b01000 '
0,
10
#30
00
#31
b00111 '
0-
0/
#32
b01000 '
b0000000000000111 *
1-
b0000000000000111 .
1/
#33
b01000 $
1%
b01001 '
1,
10
#34
00
#35
b01000 '
0+
0,
0-
0/
#36
b01001 '
b0000000000001000 *
1+
1,
1-
b0000000000001000 .
1/
#37
b01001 $
0%
b01010 '
0,
10
#38
00
#39
b01001 '
0-
0/
#40
b01010 '
b0000000000001001 *
1-
b0000000000001001 .
1/
#41
b01010 $
1%
b01011 '
1,
10
#42
00
#43
b01010 '
0+
0,
0-
0/
#44
b01011 '
b0000000000001010 *
1+
1,
1-
b0000000000001010 .
1/
#45
b01011 $
0%
b01100 '
0,
10
#46
00
#47
b01011 '
0-
0/
#48
b01100 '
b0000000000001011 *
1-
b0000000000001011 .
1/
#49
b01100 $
1%
b01101 '
1,
10
#50
00
#51
b01100 '
0+
0,
0-
0/
#52
b01101 '
b0000000000001100 *
1+
1,
1-
b0000000000001100 .
1/
#53
b01101 $
0%
b01110 '
0,
10
#54
00
#55
b01101 '
0-
0/
#56
b01110 '
b0000000000001101 *
1-
b0000000000001101 .
1/
#57
b01110 $
1%
b01111 '
1,
10
#58
00
#59
b01110 '
0+
0,
0-
0/
#60
b01111 '
b0000000000001110 *
1+
1,
1-
b0000000000001110 .
1/
#61
b01111 $
0%
b10000 '
0,
10
#62
00
#63
b01111 '
0-
0/
#64
b10000 '
b0000000000001111 *
1-
b0000000000001111 .
1/
#65
b10000 $
1%
b10001 '
1,
10
#66
00
#67
b10000 '
0+
0,
0-
0/
#68
b10001 '
b0000000000010000 *
1+
1,
1-
b0000000000010000 .
1/
#69
b10001 $
0%
b10010 '
0,
10
#70
00
#71
b10001 '
0-
0/
#72
b10010 '
b0000000000010001 *
1-
b0000000000010001 .
1/
#73
b10010 $
1%
b10011 '
1,
10
#74
00
#75
b10010 '
0+
0,
0-
0/
#76
b10011 '
b0000000000010010 *
1+
1,
1-
b0000000000010010 .
1/
#77
b10011 $
0%
b10100 '
0,
10
#78
00
#79
b10011 '
0-
0/
#80
b10100 '
b0000000000010011 *
1-
b0000000000010011 .
1/
#81
b10100 $
1%
b10101 '
1,
10
#82
00
#83
b10100 '
0+
0,
0-
0/
#84
b10101 '
b0000000000010100 *
1+
1,
1-
b0000000000010100 .
1/
#85
b10101 $
0%
b10110 '
0,
10
#86
00
#87
b10101 '
0-
0/
#88
b10110 '
b0000000000010101 *
1-
b0000000000010101 .
1/
#89
b10110 $
1%
b10111 '
1,
10
#90
00
#91
b10110 '
0+
0,
0-
0/
#92
b10111 '
b0000000000010110 *
1+
1,
1-
b0000000000010110 .
1/
#93
b10111 $
0%
b11000 '
0,
10
#94
00
#95
b10111 '
0-
0/
#96
b11000 '
b0000000000010111 *
1-
b0000000000010111 .
1/
#97
b11000 $
1%
b11001 '
1,
10
#98
00
#99
b11000 '
0+
0,
0-
0/
#100
b11001 '
b0000000000011000 *
1+
1,
1-
b0000000000011000 .
1/
#101
b11001 $
0%
b11010 '
0,
10
#102
00
#103
b11001 '
0-
0/
#104
b11010 '
b0000000000011001 *
1-
b0000000000011001 .
1/
#105
b11010 $
1%
b11011 '
1,
10
#106
00
#107
b11010 '
0+
0,
0-
0/
#108
b11011 '
b0000000000011010 *
1+
1,
1-
b0000000000011010 .
1/
#109
b11011 $
0%
b11100 '
0,
10
#110
00
#111
b11011 '
0-
0/
#112
b11100 '
b0000000000011011 *
1-
b0000000000011011 .
1/
#113
b11100 $
1%
b11101 '
1,
10
#114
00
#115
b11100 '
0+
0,
0-
0/
#116
b11101 '
b0000000000011100 *
1+
1,
1-
b0000000000011100 .
1/
#117
b11101 $
0%
b11110 '
0,
10
#118
00
#119
b11101 '
0-
0/
#120
b11110 '
b0000000000011101 *
1-
b0000000000011101 .
1/
#121
b11110 $
1%
b11111 '
1,
10
#122
00
#123
b11110 '
0+
0,
0-
0/
#124
b11111 '
b0000000000011110 *
1+
1,
1-
b0000000000011110 .
1/
#125
b11111 $
0%
0(
0,
10
#126
00
#127
1(
0-
0/
#128
0(
b0000000000011111 *
1-
b0000000000011111 .
1/
#129
b00001 &
b00001 '
1(
0)
10
#130
00
#131
b00000 '
0-
0/
#132
b00001 '
b0000000000100000 *
1-
b0000000000100000 .
1/
#133
b00001 #
b00001 $
b00010 '
1)
10
#134
00
#135
b00001 '
0-
0/
#136
b00010 '
b0000000000100001 *
1-
b0000000000100001 .
1/
#137
b00010 $
b00011 '
10
#138
00
#139
b00010 '
0-
0/
#140
b00011 '
b0000000000100010 *
1-
b0000000000100010 .
1/
#141
b00011 $
b00100 '
10
#142
00
#143
b00011 '
0-
0/
#144
b00100 '
b0000000000100011 *
1-
b0000000000100011 .
1/
#145
b00100 $
b00101 '
10
#146
00
#147
b00100 '
0-
0/
#148
b00101 '
b0000000000100100 *
1-
b0000000000100100 .
1/
#149
b00101 $
b00110 '
10
#150
00
#151
b00101 '
0-
0/
#152
b00110 '
b0000000000100101 *
1-
b0000000000100101 .
1/
#153
b00110 $
b00111 '
10
#154
00
#155
b00110 '
0-
0/
#156
b00111 '
b0000000000100110 *
1-
b0000000000100110 .
1/
#157
b00111 $
b01000 '
10
#158
00
#159
b00111 '
0-
0/
#160
b01000 '
b0000000000100111 *
1-
b0000000000100111 .
1/
#161
b01000 $
b01001 '
10
#162
00
#163
b01000 '
0-
0/
#164
b01001 '
b0000000000101000 *
1-
b0000000000101000 .
1/
#165
b01001 $
b01010 '
10
#166
00
#167
b01001 '
0-
0/
#168
b01010 '
b0000000000101001 *
1-
b0000000000101001 .
1/
#169
b01010 $
b01011 '
10
#170
00
#171
b01010 '
0-
0/
#172
b01011 '
b0000000000101010 *
1-
b0000000000101010 .
1/
#173
b01011 $
b01100 '
10
#174
00
#175
b01011 '
0-
0/
#176
b01100 '
b0000000000101011 *
1-
b0000000000101011 .
1/
#177
b01100 $
b01101 '
10
#178
00
#179
b01100 '
0-
0/
#180
b01101 '
b0000000000101100 *
1-
b0000000000101100 .
1/
#181
b01101 $
b01110 '
10
#182
00
#183
b01101 '
0-
0/
#184
b01110 '
b0000000000101101 *
1-
b0000000000101101 .
1/
#185
b01110 $
b01111 '
10
#186
00
#187
b01110 '
0-
0/
#188
b01111 '
b0000000000101110 *
1-
b0000000000101110 .
1/
#189
b01111 $
b10000 '
10
#190
00
#191
b01111 '
0-
0/
#192
b10000 '
b0000000000101111 *
1-
b0000000000101111 .
1/
#193
b10000 $
b10001 '
10
#194
00
#195
b10000 '
0-
0/
#196
b10001 '
b0000000000110000 *
1-
b0000000000110000 .
1/
#197
b10001 $
b10010 '
10
#198
00
#199
b10001 '
0-
0/
#200
b10010 '
b0000000000110001 *
1-
b0000000000110001 .
1/
#201
b10010 $
b10011 '
10
#202
00
#203
b10010 '
0-
0/
#204
b10011 '
b0000000000110010 *
1-
b0000000000110010 .
1/
#205
b10011 $
b10100 '
10
#206
00
#207
b10011 '
0-
0/
#208
b10100 '
b0000000000110011 *
1-
b0000000000110011 .
1/
#209
b10100 $
b10101 '
10
#210
00
#211
b10100 '
0-
0/
#212
b10101 '
b0000000000110100 *
1-
b0000000000110100 .
1/
#213
b10101 $
b10110 '
10
#214
00
#215
b10101 '
0-
0/
#216
b10110 '
b0000000000110101 *
1-
b0000000000110101 .
1/
#217
b10110 $
b10111 '
10
#218
00
#219
b10110 '
0-
0/
#220
b10111 '
b0000000000110110 *
1-
b0000000000110110 .
1/
#221
b10111 $
b11000 '
10
#222
00
#223
b10111 '
0-
0/
#224
b11000 '
b0000000000110111 *
1-
b0000000000110111 .
1/
#225
b11000 $
b11001 '
10
#226
00
#227
b11000 '
0-
0/
#228
b11001 '
b0000000000111000 *
1-
b0000000000111000 .
1/
#229
b11001 $
b11010 '
10
#230
00
#231
b11001 '
0-
0/
#232
b11010 '
b0000000000111001 *
1-
b0000000000111001 .
1/
#233
b11010 $
b11011 '
10
#234
00
#235
b11010 '
0-
0/
#236
b11011 '
b0000000000111010 *
1-
b0000000000111010 .
1/
#237
b11011 $
b11100 '
10
#238
00
#239
b11011 '
0-
0/
#240
b11100 '
b0000000000111011 *
1-
b0000000000111011 .
1/
#241
b11100 $
b11101 '
10
#242
00
#243
b11100 '
0-
0/
#244
b11101 '
b0000000000111100 *
1-
b0000000000111100 .
1/
#245
b11101 $
b11110 '
10
#246
00
#247
b11101 '
0-
0/
#248
b11110 '
b0000000000111101 *
1-
b0000000000111101 .
1/
#249
b11110 $
b11111 '
10
#250
00
#251
b11110 '
0-
0/
#252
b11111 '
b0000000000111110 *
1-
b0000000000111110 .
1/
#253
b11111 $
0(
10
#254
00
#255
1(
0-
0/
#256
0(
b0000000000111111 *
1-
b0000000000111111 .
1/
#257
1%
b00010 &
b00001 '
1(
0)
1,
10
#258
00
#259
b00000 '
0+
0,
0-
0/
#260
b00001 '
b0000000001000000 *
1+
1,
1-
b0000000001000000 .
1/
#261
b00010 #
b00001 $
0%
b00010 '
1)
0,
10
#262
00
#263
b00001 '
0-
0/
#264
b00010 '
b0000000001000001 *
1-
b0000000001000001 .
1/
#265
b00010 $
1%
b00011 '
1,
10
#266
00
#267
b00010 '
0+
0,
0-
0/
#268
b00011 '
b0000000001000010 *
1+
1,
1-
b0000000001000010 .
1/
#269
b00011 $
0%
b00100 '
0,
10
#270
00
#271
b00011 '
0-
0/
#272
b00100 '
b0000000001000011 *
1-
b0000000001000011 .
1/
#273
b00100 $
1%
b00101 '
1,
10
#274
00
#275
b00100 '
0+
0,
0-
0/
#276
b00101 '
b0000000001000100 *
1+
1,
1-
b0000000001000100 .
1/
#277
b00101 $
0%
b00110 '
0,
10
#278
00
#279
b00101 '
0-
0/
#280
b00110 '
b0000000001000101 *
1-
b0000000001000101 .
1/
#281
b00110 $
1%
b00111 '
1,
10
#282
00
#283
b00110 '
0+
0,
0-
0/
#284
b00111 '
b0000000001000110 *
1+
1,
1-
b0000000001000110 .
1/
#285
b00111 $
0%
b01000 '
0,
10
#286
00
#287
b00111 '
0-
0/
#288
b01000 '
b0000000001000111 *
1-
b0000000001000111 .
1/
#289
b01000 $
1%
b01001 '
1,
10
#290
00
#291
b01000 '
0+
0,
0-
0/
#292
b01001 '
b0000000001001000 *
1+
1,
1-
b0000000001001000 .
1/
#293
b01001 $
0%
b01010 '
0,
10
#294
00
#295
b01001 '
0-
0/
#296
b01010 '
b0000000001001001 *
1-
b0000000001001001 .
1/
#297
b01010 $
1%
b01011 '
1,
10
#298
00
#299
b01010 '
0+
0,
0-
0/
#300
b01011 '
b0000000001001010 *
1+
1,
1-
b0000000001001010 .
1/
#301
b01011 $
0%
b01100 '
0,
10
#302
00
#303
b01011 '
0-
0/
#304
b01100 '
b0000000001001011 *
1-
b0000000001001011 .
1/
#305
b01100 $
1%
b01101 '
1,
10
#306
00
#307
b01100 '
0+
0,
0-
0/
#308
b01101 '
b0000000001001100 *
1+
1,
1-
b0000000001001100 .
1/
#309
b01101 $
0%
b01110 '
0,
10
#310
00
#311
b01101 '
0-
0/
#312
b01110 '
b0000000001001101 *
1-
b0000000001001101 .
1/
#313
b01110 $
1%
b01111 '
1,
10
#314
00
#315
b01110 '
0+
0,
0-
0/
#316
b01111 '
b0000000001001110 *
1+
1,
1-
b0000000001001110 .
1/
#317
b01111 $
0%
b10000 '
0,
10
#318
00
#319
b01111 '
0-
0/
#320
b10000 '
b0000000001001111 *
1-
b0000000001001111 .
1/
#321
b10000 $
1%
b10001 '
1,
10
#322
00
#323
b10000 '
0+
0,
0-
0/
#324
b10001 '
b0000000001010000 *
1+
1,
1-
b0000000001010000 .
1/
#325
b10001 $
0%
b10010 '
0,
10
#326
00
#327
b10001 '
0-
0/
#328
b10010 '
b0000000001010001 *
1-
b0000000001010001 .
1/
#329
b10010 $
1%
b10011 '
1,
10
#330
00
#331
b10010 '
0+
0,
0-
0/
#332
b10011 '
b0000000001010010 *
1+
1,
1-
b0000000001010010 .
1/
#333
b10011 $
0%
b10100 '
0,
10
#334
00
#335
b10011 '
0-
0/
#336
b10100 '
b0000000001010011 *
1-
b0000000001010011 .
1/
#337
b10100 $
1%
b10101 '
1,
10
#338
00
#339
b10100 '
0+
0,
0-
0/
#340
b10101 '
b0000000001010100 *
1+
1,
1-
b0000000001010100 .
1/
#341
b10101 $
0%
b10110 '
0,
10
#342
00
#343
b10101 '
0-
0/
#344
b10110 '
b0000000001010101 *
1-
b0000000001010101 .
1/
#345
b10110 $
1%
b10111 '
1,
10
#346
00
#347
b10110 '
0+
0,
0-
0/
#348
b10111 '
b0000000001010110 *
1+
1,
1-
b0000000001010110 .
1/
#349
b10111 $
0%
b11000 '
0,
10
#350
00
#351
b10111 '
0-
0/
#352
b11000 '
b0000000001010111 *
1-
b0000000001010111 .
1/
#353
b11000 $
1%
b11001 '
1,
10
#354
00
#355
b11000 '
0+
0,
0-
0/
#356
b11001 '
b0000000001011000 *
1+
1,
1-
b0000000001011000 .
1/
#357
b11001 $
0%
b11010 '
0,
10
#358
00
#359
b11001 '
0-
0/
#360
b11010 '
b0000000001011001 *
1-
b0000000001011001 .
1/
#361
b11010 $
1%
b11011 '
1,
10
#362
00
#363
b11010 '
0+
0,
0-
0/
#364
b11011 '
b0000000001011010 *
1+
1,
1-
b0000000001011010 .
1/
#365
b11011 $
0%
b11100 '
0,
10
#366
00
#367
b11011 '
0-
0/
#368
b11100 '
b0000000001011011 *
1-
b0000000001011011 .
1/
#369
b11100 $
1%
b11101 '
1,
10
#370
00
#371
b11100 '
0+
0,
0-
0/
#372
b11101 '
b0000000001011100 *
1+
1,
1-
b0000000001011100 .
1/
#373
b11101 $
0%
b11110 '
0,
10
#374
00
#375
b11101 '
0-
0/
#376
b11110 '
b0000000001011101 *
1-
b0000000001011101 .
1/
#377
b11110 $
1%
b11111 '
1,
10
#378
00
#379
b11110 '
0+
0,
0-
0/
#380
b11111 '
b0000000001011110 *
1+
1,
1-
b0000000001011110 .
1/
#381
b11111 $
0%
0(
0,
10
#382
00
#383
1(
0-
0/
#384
0(
b0000000001011111 *
1-
b0000000001011111 .
1/
#385
b00011 &
b00001 '
1(
0)
10
#386
00
#387
b00000 '
0-
0/
#388
b00001 '
b0000000001100000 *
1-
b0000000001100000 .
1/
#389
b00011 #
b00001 $
b00010 '
1)
10
#390
00
#391
b00001 '
0-
0/
#392
b00010 '
b0000000001100001 *
1-
b0000000001100001 .
1/
#393
b00010 $
b00011 '
10
#394
00
#395
b00010 '
0-
0/
#396
b00011 '
b0000000001100010 *
1-
b0000000001100010 .
1/
#397
b00011 $
b00100 '
10
#398
00
#399
b00011 '
0-
0/
#400
b00100 '
b0000000001100011 *
1-
b0000000001100011 .
1/
#401
b00100 $
b00101 '
10
#402
00
#403
b00100 '
0-
0/
#404
b00101 '
b0000000001100100 *
1-
b0000000001100100 .
1/
#405
b00101 $
b00110 '
10
#406
00
#407
b00101 '
0-
0/
#408
b00110 '
b0000000001100101 *
1-
b0000000001100101 .
1/
#409
b00110 $
b00111 '
10
#410
00
#411
b00110 '
0-
0/
#412
b00111 '
b0000000001100110 *
1-
b0000000001100110 .
1/
#413
b00111 $
b01000 '
10
#414
00
#415
b00111 '
0-
0/
#416
b01000 '
b0000000001100111 *
1-
b0000000001100111 .
1/
#417
b01000 $
b01001 '
10
#418
00
#419
b01000 '
0-
0/
#420
b01001 '
b0000000001101000 *
1-
b0000000001101000 .
1/
#421
b01001 $
b01010 '
10
#422
00
#423
b01001 '
0-
0/
#424
b01010 '
b0000000001101001 *
1-
b0000000001101001 .
1/
#425
b01010 $
b01011 '
10
#426
00
#427
b01010 '
0-
0/
#428
b01011 '
b0000000001101010 *
1-
b0000000001101010 .
1/
#429
b01011 $
b01100 '
10
#430
00
#431
b01011 '
0-
0/
#432
b01100 '
b0000000001101011 *
1-
b0000000001101011 .
1/
#433
b01100 $
b01101 '
10
#434
00
#435
b01100 '
0-
0/
#436
b01101 '
b0000000001101100 *
1-
b0000000001101100 .
1/
#437
b01101 $
b01110 '
10
#438
00
#439
b01101 '
0-
0/
#440
b01110 '
b0000000001101101 *
1-
b0000000001101101 .
1/
#441
b01110 $
b01111 '
10
#442
00
#443
b01110 '
0-
0/
#444
b01111 '
b0000000001101110 *
1-
b0000000001101110 .
1/
#445
b01111 $
b10000 '
10
#446
00
#447
b01111 '
0-
0/
#448
b10000 '
b0000000001101111 *
1-
b0000000001101111 .
1/
#449
b10000 $
b10001 '
10
#450
00
#451
b10000 '
0-
0/
#452
b10001 '
b0000000001110000 *
1-
b0000000001110000 .
1/
#453
b10001 $
b10010 '
10
#454
00
#455
b10001 '
0-
0/
#456
b10010 '
b0000000001110001 *
1-
b0000000001110001 .
1/
#457
b10010 $
b10011 '
10
#458
00
#459
b10010 '
0-
0/
#460
b10011 '
b0000000001110010 *
1-
b0000000001110010 .
1/
#461
b10011 $
b10100 '
10
#462
00
#463
b10011 '
0-
0/
#464
b10100 '
b0000000001110011 *
1-
b0000000001110011 .
1/
#465
b10100 $
b10101 '
10
#466
00
#467
b10100 '
0-
0/
#468
b10101 '
b0000000001110100 *
1-
b0000000001110100 .
1/
#469
b10101 $
b10110 '
10
#470
00
#471
b10101 '
0-
0/
#472
b10110 '
b0000000001110101 *
1-
b0000000001110101 .
1/
#473
b10110 $
b10111 '
10
#474
00
#475
b10110 '
0-
0/
#476
b10111 '
b0000000001110110 *
1-
b0000000001110110 .
1/
#477
b10111 $
b11000 '
10
#478
00
#479
b10111 '
0-
0/
#480
b11000 '
b0000000001110111 *
1-
b0000000001110111 .
1/
#481
b11000 $
b11001 '
10
#482
00
#483
b11000 '
0-
0/
#484
b11001 '
b0000000001111000 *
1-
b0000000001111000 .
1/
#485
b11001 $
b11010 '
10
#486
00
#487
b11001 '
0-
0/
#488
b11010 '
b0000000001111001 *
1-
b0000000001111001 .
1/
#489
b11010 $
b11011 '
10
#490
00
#491
b11010 '
0-
0/
#492
b11011 '
b0000000001111010 *
1-
b0000000001111010 .
1/
#493
b11011 $
b11100 '
10
#494
00
#495
b11011 '
0-
0/
#496
b11100 '
b0000000001111011 *
1-
b0000000001111011 .
1/
#497
b11100 $
b11101 '
10
#498
00
#499
b11100 '
0-
0/
#500
b11101 '
b0000000001111100 *
1-
b0000000001111100 .
1/
#501
b11101 $
b11110 '
10
#502
00
#503
b11101 '
0-
0/
#504
b11110 '
b0000000001111101 *
1-
b0000000001111101 .
1/
#505
b11110 $
b11111 '
10
#506
00
#507
b11110 '
0-
0/
#508
b11111 '
b0000000001111110 *
1-
b0000000001111110 .
1/
#509
b11111 $
0(
10
#510
00
#511
1(
0-
0/
#512
0(
b0000000001111111 *
1-
b0000000001111111 .
1/
#513
1%
b00100 &
b00001 '
1(
0)
1,
10
#514
00
#515
b00000 '
0+
0,
0-
0/
#516
b00001 '
b0000000010000000 *
1+
1,
1-
b0000000010000000 .
1/
#517
b00100 #
b00001 $
0%
b00010 '
1)
0,
10
#518
00
#519
b00001 '
0-
0/
#520
b00010 '
b0000000010000001 *
1-
b0000000010000001 .
1/
#521
b00010 $
1%
b00011 '
1,
10
#522
00
#523
b00010 '
0+
0,
0-
0/
#524
b00011 '
b0000000010000010 *
1+
1,
1-
b0000000010000010 .
1/
#525
b00011 $
0%
b00100 '
0,
10
#526
00
#527
b00011 '
0-
0/
#528
b00100 '
b0000000010000011 *
1-
b0000000010000011 .
1/
#529
b00100 $
1%
b00101 '
1,
10
#530
00
#531
b00100 '
0+
0,
0-
0/
#532
b00101 '
b0000000010000100 *
1+
1,
1-
b0000000010000100 .
1/
#533
b00101 $
0%
b00110 '
0,
10
#534
00
#535
b00101 '
0-
0/
#536
b00110 '
b0000000010000101 *
1-
b0000000010000101 .
1/
#537
b00110 $
1%
b00111 '
1,
10
#538
00
#539
b00110 '
0+
0,
0-
0/
#540
b00111 '
b0000000010000110 *
1+
1,
1-
b0000000010000110 .
1/
#541
b00111 $
0%
b01000 '
0,
10
#542
00
#543
b00111 '
0-
0/
#544
b01000 '
b0000000010000111 *
1-
b0000000010000111 .
1/
#545
b01000 $
1%
b01001 '
1,
10
#546
00
#547
b01000 '
0+
0,
0-
0/
#548
b01001 '
b0000000010001000 *
1+
1,
1-
b0000000010001000 .
1/
#549
b01001 $
0%
b01010 '
0,
10
#550
00
#551
b01001 '
0-
0/
#552
b01010 '
b0000000010001001 *
1-
b0000000010001001 .
1/
#553
b01010 $
1%
b01011 '
1,
10
#554
00
#555
b01010 '
0+
0,
0-
0/
#556
b01011 '
b0000000010001010 *
1+
1,
1-
b0000000010001010 .
1/
#557
b01011 $
0%
b01100 '
0,
10
#558
00
#559
b01011 '
0-
0/
#560
b01100 '
b0000000010001011 *
1-
b0000000010001011 .
1/
#561
b01100 $
1%
b01101 '
1,
10
#562
00
#563
b01100 '
0+
0,
0-
0/
#564
b01101 '
b0000000010001100 *
1+
1,
1-
b0000000010001100 .
1/
#565
b01101 $
0%
b01110 '
0,
10
#566
00
#567
b01101 '
0-
0/
#568
b01110 '
b0000000010001101 *
1-
b0000000010001101 .
1/
#569
b01110 $
1%
b01111 '
1,
10
#570
00
#571
b01110 '
0+
0,
0-
0/
#572
b01111 '
b0000000010001110 *
1+
1,
1-
b0000000010001110 .
1/
#573
b01111 $
0%
b10000 '
0,
10
#574
00
#575
b01111 '
0-
0/
#576
b10000 '
b0000000010001111 *
1-
b0000000010001111 .
1/
#577
b10000 $
1%
b10001 '
1,
10
#578
00
#579
b10000 '
0+
0,
0-
0/
#580
b10001 '
b0000000010010000 *
1+
1,
1-
b0000000010010000 .
1/
#581
b10001 $
0%
b10010 '
0,
10
#582
00
#583
b10001 '
0-
0/
#584
b10010 '
b0000000010010001 *
1-
b0000000010010001 .
1/
#585
b10010 $
1%
b10011 '
1,
10
#586
00
#587
b10010 '
0+
0,
0-
0/
#588
b10011 '
b0000000010010010 *
1+
1,
1-
b0000000010010010 .
1/
#589
b10011 $
0%
b10100 '
0,
10
#590
00
#591
b10011 '
0-
0/
#592
b10100 '
b0000000010010011 *
1-
b0000000010010011 .
1/
#593
b10100 $
1%
b10101 '
1,
10
#594
00
#595
b10100 '
0+
0,
0-
0/
#596
b10101 '
b0000000010010100 *
1+
1,
1-
b0000000010010100 .
1/
#597
b10101 $
0%
b10110 '
0,
10
#598
00
#599
b10101 '
0-
0/
#600
b10110 '
b0000000010010101 *
1-
b0000000010010101 .
1/
#601
b10110 $
1%
b10111 '
1,
10
#602
00
#603
b10110 '
0+
0,
0-
0/
#604
b10111 '
b0000000010010110 *
1+
1,
1-
b0000000010010110 .
1/
#605
b10111 $
0%
b11000 '
0,
10
#606
00
#607
b10111 '
0-
0/
#608
b11000 '
b0000000010010111 *
1-
b0000000010010111 .
1/
#609
b11000 $
1%
b11001 '
1,
10
#610
00
#611
b11000 '
0+
0,
0-
0/
#612
b11001 '
b0000000010011000 *
1+
1,
1-
b0000000010011000 .
1/
#613
b11001 $
0%
b11010 '
0,
10
#614
00
#615
b11001 '
0-
0/
#616
b11010 '
b0000000010011001 *
1-
b0000000010011001 .
1/
#617
b11010 $
1%
b11011 '
1,
10
#618
00
#619
b11010 '
0+
0,
0-
0/
#620
b11011 '
b0000000010011010 *
1+
1,
1-
b0000000010011010 .
1/
#621
b11011 $
0%
b11100 '
0,
10
#622
00
#623
b11011 '
0-
0/
#624
b11100 '
b0000000010011011 *
1-
b0000000010011011 .
1/
#625
b11100 $
1%
b11101 '
1,
10
#626
00
#627
b11100 '
0+
0,
0-
0/
#628
b11101 '
b0000000010011100 *
1+
1,
1-
b0000000010011100 .
1/
#629
b11101 $
0%
b11110 '
0,
10
#630
00
#631
b11101 '
0-
0/
#632
b11110 '
b0000000010011101 *
1-
b0000000010011101 .
1/
#633
b11110 $
1%
b11111 '
1,
10
#634
00
#635
b11110 '
0+
0,
0-
0/
#636
b11111 '
b0000000010011110 *
1+
1,
1-
b0000000010011110 .
1/
#637
b11111 $
0%
0(
0,
10
#638
00
#639
1(
0-
0/
#640
0(
b0000000010011111 *
1-
b0000000010011111 .
1/
#641
b00101 &
b00001 '
1(
0)
10
#642
00
#643
b00000 '
0-
0/
#644
b00001 '
b0000000010100000 *
1-
b0000000010100000 .
1/
#645
b00101 #
b00001 $
b00010 '
1)
10
#646
00
#647
b00001 '
0-
0/
#648
b00010 '
b0000000010100001 *
1-
b0000000010100001 .
1/
#649
b00010 $
b00011 '
10
#650
00
#651
b00010 '
0-
0/
#652
b00011 '
b0000000010100010 *
1-
b0000000010100010 .
1/
#653
b00011 $
b00100 '
10
#654
00
#655
b00011 '
0-
0/
#656
b00100 '
b0000000010100011 *
1-
b0000000010100011 .
1/
#657
b00100 $
b00101 '
10
#658
00
#659
b00100 '
0-
0/
#660
b00101 '
b0000000010100100 *
1-
b0000000010100100 .
1/
#661
b00101 $
b00110 '
10
#662
00
#663
b00101 '
0-
0/
#664
b00110 '
b0000000010100101 *
1-
b0000000010100101 .
1/
#665
b00110 $
b00111 '
10
#666
00
#667
b00110 '
0-
0/
#668
b00111 '
b0000000010100110 *
1-
b0000000010100110 .
1/
