build/DownsampleChannel.v
module DownsampleChannel
(
  output data_out_valid,
  output data_in_ready,
  output [16-1:0] data_out_data,
  input [16-1:0] data_in_data,
  input data_in_valid,
  input data_out_ready,
  input CLK
);

  reg [16-1:0] data;
  reg [16-1:0] data_next;
  reg [5-1:0] x;
  reg [5-1:0] x_next;
  reg [5-1:0] y;
  reg [5-1:0] y_next;
  reg keep;
  reg keep_next;
  reg [3-1:0] yield_state;
  reg [3-1:0] yield_state_next;

  initial begin
    x = 0;
    x_next = 0;
    y = 0;
    y_next = 0;
    yield_state = 0;
  end


  always @(*) begin
    keep_next = keep;
    y_next = y;
    x_next = x;
    data_next = data;
    if(yield_state == 0) begin
      data_in_ready = 0;
      data_out_valid = 0;
      data_out_data = 0;
      y_next = 0;
      x_next = 0;
      keep_next = (x_next % 2 == 0) & (y_next % 2 == 0);
      if(keep_next & ~data_out_ready | ~data_in_valid) begin
        yield_state_next = 2;
      end else begin
        data_in_ready = 1;
        if(data_in_valid) begin
          data_next = data_in_data;
          if(keep_next) begin
            data_out_valid = 1;
            data_out_data = data_next;
            if(data_out_ready) begin
              yield_state_next = 5;
            end 
          end else begin
            yield_state_next = 5;
          end
        end 
      end
    end else if(yield_state == 1) begin
      data_in_ready = 0;
      data_out_valid = 0;
      data_out_data = 0;
      y_next = 0;
      x_next = 0;
      keep_next = (x_next % 2 == 0) & (y_next % 2 == 0);
      if(keep_next & ~data_out_ready | ~data_in_valid) begin
        yield_state_next = 2;
      end else begin
        data_in_ready = 1;
        if(data_in_valid) begin
          data_next = data_in_data;
          if(keep_next) begin
            data_out_valid = 1;
            data_out_data = data_next;
            if(data_out_ready) begin
              yield_state_next = 5;
            end 
          end else begin
            yield_state_next = 5;
          end
        end 
      end
    end else if(yield_state == 2) begin
      data_in_ready = 0;
      data_out_valid = 0;
      data_out_data = 0;
      if(keep_next & ~data_out_ready | ~data_in_valid) begin
        yield_state_next = 2;
      end else begin
        data_in_ready = 1;
        if(data_in_valid) begin
          data_next = data_in_data;
          if(keep_next) begin
            data_out_valid = 1;
            data_out_data = data_next;
            if(data_out_ready) begin
              yield_state_next = 5;
            end 
          end else begin
            yield_state_next = 5;
          end
        end 
      end
    end else if(yield_state == 3) begin
      data_in_ready = 0;
      data_out_valid = 0;
      data_out_data = 0;
      data_in_ready = 1;
      if(data_in_valid) begin
        data_next = data_in_data;
        if(keep_next) begin
          data_out_valid = 1;
          data_out_data = data_next;
          if(data_out_ready) begin
            yield_state_next = 5;
          end else begin
            yield_state_next = 4;
          end
        end else begin
          yield_state_next = 5;
        end
      end else begin
        yield_state_next = 3;
      end
    end else if(yield_state == 4) begin
      data_in_ready = 0;
      data_out_valid = 0;
      data_out_data = 0;
      data_out_valid = 1;
      data_out_data = data_next;
      if(data_out_ready) begin
        yield_state_next = 5;
      end else begin
        yield_state_next = 4;
      end
    end else if(yield_state == 5) begin
      data_in_ready = 0;
      data_out_valid = 0;
      data_out_data = 0;
      if(x_next == 31) begin
        if(y_next == 31) begin
          y_next = 0;
          x_next = 0;
          keep_next = (x_next % 2 == 0) & (y_next % 2 == 0);
          if(keep_next & ~data_out_ready | ~data_in_valid) begin
            yield_state_next = 2;
          end else begin
            data_in_ready = 1;
            if(data_in_valid) begin
              data_next = data_in_data;
              if(keep_next) begin
                data_out_valid = 1;
                data_out_data = data_next;
                if(data_out_ready) begin
                  yield_state_next = 5;
                end 
              end else begin
                yield_state_next = 5;
              end
            end 
          end
        end else begin
          y_next = y_next + 1;
          x_next = 0;
          keep_next = (x_next % 2 == 0) & (y_next % 2 == 0);
          if(keep_next & ~data_out_ready | ~data_in_valid) begin
            yield_state_next = 2;
          end else begin
            data_in_ready = 1;
            if(data_in_valid) begin
              data_next = data_in_data;
              if(keep_next) begin
                data_out_valid = 1;
                data_out_data = data_next;
                if(data_out_ready) begin
                  yield_state_next = 5;
                end 
              end else begin
                yield_state_next = 5;
              end
            end 
          end
        end
      end else begin
        x_next = x_next + 1;
        keep_next = (x_next % 2 == 0) & (y_next % 2 == 0);
        if(keep_next & ~data_out_ready | ~data_in_valid) begin
          yield_state_next = 2;
        end else begin
          data_in_ready = 1;
          if(data_in_valid) begin
            data_next = data_in_data;
            if(keep_next) begin
              data_out_valid = 1;
              data_out_data = data_next;
              if(data_out_ready) begin
                yield_state_next = 5;
              end 
            end else begin
              yield_state_next = 5;
            end
          end 
        end
      end
    end 
  end


  always @(posedge CLK) begin
    data = data_next;
    x = x_next;
    y = y_next;
    keep = keep_next;
    yield_state = yield_state_next;
  end


endmodule

build/logs/DownsampleChannel.vcd
$version Generated by VerilatedVcd $end
$date Thu Sep 26 09:49:09 2019
 $end
$timescale   1ns $end

 $scope module TOP $end
  $var wire  1 3 CLK $end
  $var wire 16 0 data_in_data [15:0] $end
  $var wire  1 . data_in_ready $end
  $var wire  1 1 data_in_valid $end
  $var wire 16 / data_out_data [15:0] $end
  $var wire  1 2 data_out_ready $end
  $var wire  1 - data_out_valid $end
  $scope module DownsampleChannel $end
   $var wire  1 3 CLK $end
   $var wire 16 + data [15:0] $end
   $var wire 16 0 data_in_data [15:0] $end
   $var wire  1 . data_in_ready $end
   $var wire  1 1 data_in_valid $end
   $var wire 16 & data_next [15:0] $end
   $var wire 16 / data_out_data [15:0] $end
   $var wire  1 2 data_out_ready $end
   $var wire  1 - data_out_valid $end
   $var wire  1 , keep $end
   $var wire  1 ) keep_next $end
   $var wire  5 # x [4:0] $end
   $var wire  5 ' x_next [4:0] $end
   $var wire  5 $ y [4:0] $end
   $var wire  5 ( y_next [4:0] $end
   $var wire  3 % yield_state [2:0] $end
   $var wire  3 * yield_state_next [2:0] $end
  $upscope $end
 $upscope $end
$enddefinitions $end


#1
b00000 #
b00000 $
b010 %
b0000000000000000 &
b00000 '
b00000 (
1)
b010 *
b0000000000000000 +
1,
0-
0.
b0000000000000000 /
b0000000000000000 0
01
02
13
#2
03
#3
12
#4
13
#5
03
#6
11
02
#7
13
#8
03
#9
01
#10
13
#11
03
#12
12
#13
13
#14
03
#15
11
02
#16
13
#17
03
#18
01
#19
13
#20
03
#21
#22
13
#23
03
#24
b101 *
1-
1.
11
12
#25
b101 %
b00001 '
0)
0-
13
#26
03
#27
b0000000000000001 &
b0000000000000001 0
02
#28
b00001 #
b00010 '
1)
b010 *
b0000000000000001 +
0,
0.
13
#29
03
#30
b0000000000000010 0
#31
b00010 #
b010 %
1,
13
#32
03
#33
01
#34
13
#35
03
#36
11
#37
13
#38
03
#39
b0000000000000010 &
b101 *
1-
1.
b0000000000000010 /
12
#40
b101 %
b00011 '
0)
b0000000000000010 +
0-
b0000000000000000 /
13
#41
03
#42
b0000000000000011 &
b0000000000000011 0
#43
b00011 #
b00100 '
1)
b0000000000000011 +
0,
1-
b0000000000000011 /
13
#44
03
#45
b010 *
0-
0.
b0000000000000000 /
b0000000000000100 0
02
#46
b00100 #
b010 %
1,
13
#47
03
#48
01
#49
13
#50
03
#51
12
#52
13
#53
03
#54
b0000000000000100 &
b101 *
1-
1.
b0000000000000100 /
11
#55
b101 %
b00101 '
0)
b0000000000000100 +
0-
b0000000000000000 /
13
#56
03
#57
b0000000000000101 &
b0000000000000101 0
#58
b00101 #
b00110 '
1)
b0000000000000101 +
0,
1-
b0000000000000101 /
13
#59
03
#60
b010 *
0-
0.
b0000000000000000 /
b0000000000000110 0
01
#61
b00110 #
b010 %
1,
13
#62
03
#63
02
#64
13
#65
03
#66
12
#67
13
#68
03
#69
#70
13
#71
03
#72
#73
13
#74
03
#75
#76
13
#77
03
#78
11
02
#79
13
#80
03
#81
b0000000000000110 &
b101 *
1-
1.
b0000000000000110 /
12
#82
b101 %
b00111 '
0)
b0000000000000110 +
0-
b0000000000000000 /
13
#83
03
#84
b0000000000000111 &
b0000000000000111 0
02
#85
b00111 #
b01000 '
1)
b010 *
b0000000000000111 +
0,
0.
13
#86
03
#87
b0000000000001000 &
b101 *
1-
1.
b0000000000001000 /
b0000000000001000 0
12
#88
b01000 #
b01001 '
0)
b0000000000001000 +
1,
0-
b0000000000000000 /
13
#89
03
#90
b010 *
0.
b0000000000001001 0
01
#91
b01001 #
b010 %
0,
13
#92
03
#93
b0000000000001001 &
b101 *
1.
11
#94
b101 %
b01010 '
1)
b0000000000001001 +
1-
b0000000000001001 /
13
#95
03
#96
b0000000000001010 &
b0000000000001010 /
b0000000000001010 0
#97
b01010 #
b01011 '
0)
b0000000000001010 +
1,
0-
b0000000000000000 /
13
#98
03
#99
b0000000000001011 &
b0000000000001011 0
02
#100
b01011 #
b01100 '
1)
b010 *
b0000000000001011 +
0,
0.
13
#101
03
#102
b0000000000001100 0
01
#103
b01100 #
b010 %
1,
13
#104
03
#105
b0000000000001100 &
b101 *
1-
1.
b0000000000001100 /
11
12
#106
b101 %
b01101 '
0)
b0000000000001100 +
0-
b0000000000000000 /
13
#107
03
#108
b010 *
0.
b0000000000001101 0
01
#109
b01101 #
b010 %
0,
13
#110
03
#111
b0000000000001101 &
b101 *
1.
11
02
#112
b101 %
b01110 '
1)
b010 *
b0000000000001101 +
0.
13
#113
03
#114
b0000000000001110 0
01
#115
b01110 #
b010 %
1,
13
#116
03
#117
b0000000000001110 &
b101 *
1-
1.
b0000000000001110 /
11
12
#118
b101 %
b01111 '
0)
b0000000000001110 +
0-
b0000000000000000 /
13
#119
03
#120
b010 *
0.
b0000000000001111 0
01
#121
b01111 #
b010 %
0,
13
#122
03
#123
b0000000000001111 &
b101 *
1.
11
02
#124
b101 %
b10000 '
1)
b010 *
b0000000000001111 +
0.
13
#125
03
#126
b0000000000010000 0
01
#127
b10000 #
b010 %
1,
13
#128
03
#129
#130
13
#131
03
#132
11
#133
13
#134
03
#135
#136
13
#137
03
#138
01
12
#139
13
#140
03
#141
02
#142
13
#143
03
#144
12
#145
13
#146
03
#147
#148
13
#149
03
#150
#151
13
#152
03
#153
11
02
#154
13
#155
03
#156
01
#157
13
#158
03
#159
b0000000000010000 &
b101 *
1-
1.
b0000000000010000 /
11
12
#160
b101 %
b10001 '
0)
b0000000000010000 +
0-
b0000000000000000 /
13
#161
03
#162
b010 *
0.
b0000000000010001 0
01
#163
b10001 #
b010 %
0,
13
#164
03
#165
#166
13
#167
03
#168
b0000000000010001 &
b101 *
1.
11
02
#169
b101 %
b10010 '
1)
b010 *
b0000000000010001 +
0.
13
#170
03
#171
b0000000000010010 0
01
#172
b10010 #
b010 %
1,
13
#173
03
#174
#175
13
#176
03
#177
12
#178
13
#179
03
#180
11
02
#181
13
#182
03
#183
01
12
#184
13
#185
03
#186
11
02
#187
13
#188
03
#189
b0000000000010010 &
b101 *
1-
1.
b0000000000010010 /
12
#190
b101 %
b10011 '
0)
b0000000000010010 +
0-
b0000000000000000 /
13
#191
03
#192
b0000000000010011 &
b0000000000010011 0
#193
b10011 #
b10100 '
1)
b0000000000010011 +
0,
1-
b0000000000010011 /
13
#194
03
#195
b0000000000010100 &
b0000000000010100 /
b0000000000010100 0
#196
b10100 #
b10101 '
0)
b0000000000010100 +
1,
0-
b0000000000000000 /
13
#197
03
#198
b010 *
0.
b0000000000010101 0
01
02
#199
b10101 #
b010 %
0,
13
#200
03
#201
b0000000000010101 &
b101 *
1.
11
#202
b101 %
b10110 '
1)
b010 *
b0000000000010101 +
0.
13
#203
03
#204
b0000000000010110 0
01
12
#205
b10110 #
b010 %
1,
13
#206
03
#207
b0000000000010110 &
b101 *
1-
1.
b0000000000010110 /
11
#208
b101 %
b10111 '
0)
b0000000000010110 +
0-
b0000000000000000 /
13
#209
03
#210
b0000000000010111 &
b0000000000010111 0
#211
b10111 #
b11000 '
1)
b0000000000010111 +
0,
1-
b0000000000010111 /
13
#212
03
#213
b0000000000011000 &
b0000000000011000 /
b0000000000011000 0
#214
b11000 #
b11001 '
0)
b0000000000011000 +
1,
0-
b0000000000000000 /
13
#215
03
#216
b0000000000011001 &
b0000000000011001 0
02
#217
b11001 #
b11010 '
1)
b010 *
b0000000000011001 +
0,
0.
13
#218
03
#219
b0000000000011010 &
b101 *
1-
1.
b0000000000011010 /
b0000000000011010 0
12
#220
b11010 #
b11011 '
0)
b0000000000011010 +
1,
0-
b0000000000000000 /
13
#221
03
#222
b0000000000011011 &
b0000000000011011 0
02
#223
b11011 #
b11100 '
1)
b010 *
b0000000000011011 +
0,
0.
13
#224
03
#225
b0000000000011100 0
#226
b11100 #
b010 %
1,
13
#227
03
#228
01
12
#229
13
#230
03
#231
02
#232
13
#233
03
#234
b0000000000011100 &
b101 *
1-
1.
b0000000000011100 /
11
12
#235
b101 %
b11101 '
0)
b0000000000011100 +
0-
b0000000000000000 /
13
#236
03
#237
b0000000000011101 &
b0000000000011101 0
#238
b11101 #
b11110 '
1)
b0000000000011101 +
0,
1-
b0000000000011101 /
13
#239
03
#240
b010 *
0-
0.
b0000000000000000 /
b0000000000011110 0
01
02
#241
b11110 #
b010 %
1,
13
#242
03
#243
b0000000000011110 &
b101 *
1-
1.
b0000000000011110 /
11
12
#244
b101 %
b11111 '
0)
b0000000000011110 +
0-
b0000000000000000 /
13
#245
03
#246
b0000000000011111 &
b0000000000011111 0
02
#247
b11111 #
b00000 '
b00001 (
b0000000000011111 +
0,
13
#248
03
#249
b010 *
0.
b0000000000100000 0
01
12
#250
b00000 #
b00001 $
b010 %
13
#251
03
#252
02
#253
13
#254
03
#255
#256
13
#257
03
#258
#259
13
#260
03
#261
b0000000000100000 &
b101 *
1.
11
12
#262
b101 %
b00001 '
b0000000000100000 +
13
#263
03
#264
b0000000000100001 &
b0000000000100001 0
02
#265
b00001 #
b00010 '
b0000000000100001 +
13
#266
03
#267
b0000000000100010 &
b0000000000100010 0
12
#268
b00010 #
b00011 '
b0000000000100010 +
13
#269
03
#270
b010 *
0.
b0000000000100011 0
01
02
#271
b00011 #
b010 %
13
#272
03
#273
b0000000000100011 &
b101 *
1.
11
12
#274
b101 %
b00100 '
b0000000000100011 +
13
#275
03
#276
b010 *
0.
b0000000000100100 0
01
02
#277
b00100 #
b010 %
13
#278
03
#279
#280
13
#281
03
#282
b0000000000100100 &
b101 *
1.
11
12
#283
b101 %
b00101 '
b0000000000100100 +
13
#284
03
#285
b0000000000100101 &
b0000000000100101 0
#286
b00101 #
b00110 '
b0000000000100101 +
13
#287
03
#288
b010 *
0.
b0000000000100110 0
01
#289
b00110 #
b010 %
13
#290
03
#291
#292
13
#293
03
#294
b0000000000100110 &
b101 *
1.
11
02
#295
b101 %
b00111 '
b0000000000100110 +
13
#296
03
#297
b0000000000100111 &
b0000000000100111 0
#298
b00111 #
b01000 '
b0000000000100111 +
13
#299
03
#300
b0000000000101000 &
b0000000000101000 0
12
#301
b01000 #
b01001 '
b0000000000101000 +
13
#302
03
#303
b010 *
0.
b0000000000101001 0
01
#304
b01001 #
b010 %
13
#305
03
#306
#307
13
#308
03
#309
b0000000000101001 &
b101 *
1.
11
#310
b101 %
b01010 '
b0000000000101001 +
13
#311
03
#312
b010 *
0.
b0000000000101010 0
01
02
#313
b01010 #
b010 %
13
#314
03
#315
b0000000000101010 &
b101 *
1.
11
#316
b101 %
b01011 '
b0000000000101010 +
13
#317
03
#318
b010 *
0.
b0000000000101011 0
01
12
#319
b01011 #
b010 %
13
#320
03
#321
#322
13
#323
03
#324
b0000000000101011 &
b101 *
1.
11
#325
b101 %
b01100 '
b0000000000101011 +
13
#326
03
#327
b010 *
0.
b0000000000101100 0
01
02
#328
b01100 #
b010 %
13
#329
03
#330
#331
13
#332
03
#333
12
#334
13
#335
03
#336
#337
13
#338
03
#339
02
#340
13
#341
03
#342
b0000000000101100 &
b101 *
1.
11
12
#343
b101 %
b01101 '
b0000000000101100 +
13
#344
03
#345
b010 *
0.
b0000000000101101 0
01
#346
b01101 #
b010 %
13
#347
03
#348
b0000000000101101 &
b101 *
1.
11
#349
b101 %
b01110 '
b0000000000101101 +
13
#350
03
#351
b0000000000101110 &
b0000000000101110 0
#352
b01110 #
b01111 '
b0000000000101110 +
13
#353
03
#354
b0000000000101111 &
b0000000000101111 0
#355
b01111 #
b10000 '
b0000000000101111 +
13
#356
03
#357
b010 *
0.
b0000000000110000 0
01
#358
b10000 #
b010 %
13
#359
03
#360
b0000000000110000 &
b101 *
1.
11
02
#361
b101 %
b10001 '
b0000000000110000 +
13
#362
03
#363
b010 *
0.
b0000000000110001 0
01
12
#364
b10001 #
b010 %
13
#365
03
#366
#367
13
#368
03
#369
b0000000000110001 &
b101 *
1.
11
#370
b101 %
b10010 '
b0000000000110001 +
13
#371
03
#372
b0000000000110010 &
b0000000000110010 0
#373
b10010 #
b10011 '
b0000000000110010 +
13
#374
03
#375
b0000000000110011 &
b0000000000110011 0
02
#376
b10011 #
b10100 '
b0000000000110011 +
13
#377
03
#378
b010 *
0.
b0000000000110100 0
01
12
#379
b10100 #
b010 %
13
#380
03
#381
b0000000000110100 &
b101 *
1.
11
02
#382
b101 %
b10101 '
b0000000000110100 +
13
#383
03
#384
b010 *
0.
b0000000000110101 0
01
12
#385
b10101 #
b010 %
13
#386
03
#387
#388
13
#389
03
#390
b0000000000110101 &
b101 *
1.
11
#391
b101 %
b10110 '
b0000000000110101 +
13
#392
03
#393
b010 *
0.
b0000000000110110 0
01
02
#394
b10110 #
b010 %
13
#395
03
#396
b0000000000110110 &
b101 *
1.
11
#397
b101 %
b10111 '
b0000000000110110 +
13
#398
03
#399
b010 *
0.
b0000000000110111 0
01
#400
b10111 #
b010 %
13
#401
03
#402
b0000000000110111 &
b101 *
1.
11
#403
b101 %
b11000 '
b0000000000110111 +
13
#404
03
#405
b0000000000111000 &
b0000000000111000 0
12
#406
b11000 #
b11001 '
b0000000000111000 +
13
#407
03
#408
b010 *
0.
b0000000000111001 0
01
#409
b11001 #
b010 %
13
#410
03
#411
b0000000000111001 &
b101 *
1.
11
02
#412
b101 %
b11010 '
b0000000000111001 +
13
#413
03
#414
b010 *
0.
b0000000000111010 0
01
#415
b11010 #
b010 %
13
#416
03
#417
12
#418
13
#419
03
#420
b0000000000111010 &
b101 *
1.
11
02
#421
b101 %
b11011 '
b0000000000111010 +
13
#422
03
#423
b0000000000111011 &
b0000000000111011 0
#424
b11011 #
b11100 '
b0000000000111011 +
13
#425
03
#426
b010 *
0.
b0000000000111100 0
01
#427
b11100 #
b010 %
13
#428
03
#429
12
#430
13
#431
03
#432
#433
13
#434
03
#435
b0000000000111100 &
b101 *
1.
11
02
#436
b101 %
b11101 '
b0000000000111100 +
13
#437
03
#438
b010 *
0.
b0000000000111101 0
01
#439
b11101 #
b010 %
13
#440
03
#441
12
#442
13
#443
03
#444
b0000000000111101 &
b101 *
1.
11
#445
b101 %
b11110 '
b0000000000111101 +
13
#446
03
#447
b0000000000111110 &
b0000000000111110 0
02
#448
b11110 #
b11111 '
b0000000000111110 +
13
#449
03
#450
b010 *
0.
b0000000000111111 0
01
#451
b11111 #
b010 %
13
#452
03
#453
12
#454
13
#455
03
#456
02
#457
13
#458
03
#459
#460
13
#461
03
#462
#463
13
#464
03
#465
b0000000000111111 &
b101 *
1.
11
#466
b101 %
b00000 '
b00010 (
1)
b010 *
b0000000000111111 +
0.
13
#467
03
#468
b0000000001000000 0
01
#469
b00000 #
b00010 $
b010 %
1,
13
#470
03
#471
11
#472
13
#473
03
#474
#475
13
#476
03
#477
b0000000001000000 &
b101 *
1-
1.
b0000000001000000 /
12
#478
b101 %
b00001 '
0)
b0000000001000000 +
0-
b0000000000000000 /
13
#479
03
#480
b010 *
0.
b0000000001000001 0
01
#481
b00001 #
b010 %
0,
13
#482
03
#483
02
#484
13
#485
03
#486
b0000000001000001 &
b101 *
1.
11
12
#487
b101 %
b00010 '
1)
b0000000001000001 +
1-
b0000000001000001 /
13
#488
03
#489
b010 *
0-
0.
b0000000000000000 /
b0000000001000010 0
02
#490
b00010 #
b010 %
1,
13
#491
03
#492
01
12
#493
13
#494
03
#495
11
02
#496
13
#497
03
#498
b0000000001000010 &
b101 *
1-
1.
b0000000001000010 /
12
#499
b101 %
b00011 '
0)
b0000000001000010 +
0-
b0000000000000000 /
13
#500
03
#501
b010 *
0.
b0000000001000011 0
01
#502
b00011 #
b010 %
0,
13
#503
03
#504
02
#505
13
#506
03
#507
b0000000001000011 &
b101 *
1.
11
#508
b101 %
b00100 '
1)
b010 *
b0000000001000011 +
0.
13
#509
03
#510
b0000000001000100 0
01
12
#511
b00100 #
b010 %
1,
13
#512
03
#513
02
#514
13
#515
03
#516
11
#517
13
#518
03
#519
b0000000001000100 &
b101 *
1-
1.
b0000000001000100 /
12
#520
b101 %
b00101 '
0)
b0000000001000100 +
0-
b0000000000000000 /
13
#521
03
#522
b010 *
0.
b0000000001000101 0
01
02
#523
b00101 #
b010 %
0,
13
#524
03
#525
12
#526
13
#527
03
#528
b0000000001000101 &
b101 *
1.
11
#529
b101 %
b00110 '
1)
b0000000001000101 +
1-
b0000000001000101 /
13
#530
03
#531
b010 *
0-
0.
b0000000000000000 /
b0000000001000110 0
02
#532
b00110 #
b010 %
1,
13
#533
03
#534
01
#535
13
#536
03
#537
12
#538
13
#539
03
#540
#541
13
#542
03
#543
#544
13
#545
03
#546
02
#547
13
#548
03
#549
12
#550
13
#551
03
#552
#553
13
#554
03
#555
11
02
#556
13
#557
03
#558
01
12
#559
13
#560
03
#561
#562
13
#563
03
#564
11
02
#565
13
#566
03
#567
01
#568
13
#569
03
#570
11
#571
13
#572
03
#573
01
#574
13
#575
03
#576
b0000000001000110 &
b101 *
1-
1.
b0000000001000110 /
11
12
#577
b101 %
b00111 '
0)
b0000000001000110 +
0-
b0000000000000000 /
13
#578
03
#579
b010 *
0.
b0000000001000111 0
01
02
#580
b00111 #
b010 %
0,
13
#581
03
#582
b0000000001000111 &
b101 *
1.
11
12
#583
b101 %
b01000 '
1)
b0000000001000111 +
1-
b0000000001000111 /
13
#584
03
#585
b010 *
0-
0.
b0000000000000000 /
b0000000001001000 0
02
#586
b01000 #
b010 %
1,
13
#587
03
#588
01
#589
13
#590
03
#591
12
#592
13
#593
03
#594
11
02
#595
13
#596
03
#597
b0000000001001000 &
b101 *
1-
1.
b0000000001001000 /
12
#598
b101 %
b01001 '
0)
b0000000001001000 +
0-
b0000000000000000 /
13
#599
03
#600
b010 *
0.
b0000000001001001 0
01
02
#601
b01001 #
b010 %
0,
13
#602
03
#603
#604
13
#605
03
#606
12
#607
13
#608
03
#609
02
#610
13
#611
03
#612
b0000000001001001 &
b101 *
1.
11
#613
b101 %
b01010 '
1)
b010 *
b0000000001001001 +
0.
13
#614
03
#615
b0000000001001010 0
01
#616
b01010 #
b010 %
1,
13
#617
03
#618
11
#619
13
#620
03
#621
01
12
#622
13
#623
03
#624
#625
13
#626
03
#627
#628
13
#629
03
#630
11
02
#631
13
#632
03
#633
01
12
#634
13
#635
03
#636
02
#637
13
#638
03
#639
12
#640
13
#641
03
#642
#643
13
#644
03
#645
b0000000001001010 &
b101 *
1-
1.
b0000000001001010 /
11
#646
b101 %
b01011 '
0)
b0000000001001010 +
0-
b0000000000000000 /
13
#647
03
#648
b0000000001001011 &
b0000000001001011 0
02
#649
b01011 #
b01100 '
1)
b010 *
b0000000001001011 +
0,
0.
13
#650
03
#651
b0000000001001100 0
01
12
#652
b01100 #
b010 %
1,
13
#653
03
#654
02
#655
13
#656
03
#657
b0000000001001100 &
b101 *
1-
1.
b0000000001001100 /
11
12
#658
b101 %
b01101 '
0)
b0000000001001100 +
0-
b0000000000000000 /
13
#659
03
#660
b010 *
0.
b0000000001001101 0
01
#661
b01101 #
b010 %
0,
13
#662
03
#663
b0000000001001101 &
b101 *
1.
11
#664
b101 %
b01110 '
1)
b0000000001001101 +
1-
b0000000001001101 /
13
#665
03
#666
b010 *
0-
0.
b0000000000000000 /
b0000000001001110 0
02
#667
b01110 #
b010 %
1,
13
#668
03
#669
#670
13
#671
03
#672
b0000000001001110 &
b101 *
1-
1.
b0000000001001110 /
12
#673
b101 %
b01111 '
0)
b0000000001001110 +
0-
b0000000000000000 /
13
#674
03
#675
b010 *
0.
b0000000001001111 0
01
#676
b01111 #
b010 %
0,
13
#677
03
#678
b0000000001001111 &
b101 *
1.
11
#679
b101 %
b10000 '
1)
b0000000001001111 +
1-
b0000000001001111 /
13
#680
03
#681
b010 *
0-
0.
b0000000000000000 /
b0000000001010000 0
01
#682
b10000 #
b010 %
1,
13
#683
03
#684
02
#685
13
#686
03
#687
b0000000001010000 &
b101 *
1-
1.
b0000000001010000 /
11
12
#688
b101 %
b10001 '
0)
b0000000001010000 +
0-
b0000000000000000 /
13
#689
03
#690
b010 *
0.
b0000000001010001 0
01
02
#691
b10001 #
b010 %
0,
13
#692
03
#693
12
#694
13
#695
03
#696
#697
13
#698
03
#699
#700
13
#701
03
#702
#703
13
#704
03
#705
#706
13
#707
03
#708
b0000000001010001 &
b101 *
1.
11
02
#709
b101 %
b10010 '
1)
b010 *
b0000000001010001 +
0.
13
#710
03
#711
b0000000001010010 0
01
12
#712
b10010 #
b010 %
1,
13
#713
03
#714
02
#715
13
#716
03
#717
b0000000001010010 &
b101 *
1-
1.
b0000000001010010 /
11
12
#718
b101 %
b10011 '
0)
b0000000001010010 +
0-
b0000000000000000 /
13
#719
03
#720
b010 *
0.
b0000000001010011 0
01
#721
b10011 #
b010 %
0,
13
#722
03
#723
b0000000001010011 &
b101 *
1.
11
02
#724
b101 %
b10100 '
1)
b010 *
b0000000001010011 +
0.
13
#725
03
#726
b0000000001010100 0
#727
b10100 #
b010 %
1,
13
#728
03
#729
#730
13
#731
03
#732
#733
13
#734
03
#735
b0000000001010100 &
b101 *
1-
1.
b0000000001010100 /
12
#736
b101 %
b10101 '
0)
b0000000001010100 +
0-
b0000000000000000 /
13
#737
03
#738
b010 *
0.
b0000000001010101 0
01
02
#739
b10101 #
b010 %
0,
13
#740
03
#741
b0000000001010101 &
b101 *
1.
11
12
#742
b101 %
b10110 '
1)
b0000000001010101 +
1-
b0000000001010101 /
13
#743
03
#744
b010 *
0-
0.
b0000000000000000 /
b0000000001010110 0
01
#745
b10110 #
b010 %
1,
13
#746
03
#747
#748
13
#749
03
#750
11
02
#751
13
#752
03
#753
b0000000001010110 &
b101 *
1-
1.
b0000000001010110 /
12
#754
b101 %
b10111 '
0)
b0000000001010110 +
0-
b0000000000000000 /
13
#755
03
#756
b010 *
0.
b0000000001010111 0
01
02
#757
b10111 #
b010 %
0,
13
#758
03
#759
12
#760
13
#761
03
#762
b0000000001010111 &
b101 *
1.
11
#763
b101 %
b11000 '
1)
b0000000001010111 +
1-
b0000000001010111 /
13
#764
03
#765
b010 *
0-
0.
b0000000000000000 /
b0000000001011000 0
02
#766
b11000 #
b010 %
1,
13
#767
03
#768
#769
13
#770
03
#771
b0000000001011000 &
b101 *
1-
1.
b0000000001011000 /
12
#772
b101 %
b11001 '
0)
b0000000001011000 +
0-
b0000000000000000 /
13
#773
03
#774
b010 *
0.
b0000000001011001 0
01
#775
b11001 #
b010 %
0,
13
#776
03
#777
#778
13
#779
03
#780
02
#781
13
#782
03
#783
b0000000001011001 &
b101 *
1.
11
12
#784
b101 %
b11010 '
1)
b0000000001011001 +
1-
b0000000001011001 /
13
#785
03
#786
b0000000001011010 &
b0000000001011010 /
b0000000001011010 0
#787
b11010 #
b11011 '
0)
b0000000001011010 +
1,
0-
b0000000000000000 /
13
#788
03
#789
b010 *
0.
b0000000001011011 0
01
#790
b11011 #
b010 %
0,
13
#791
03
#792
#793
13
#794
03
#795
b0000000001011011 &
b101 *
1.
11
02
#796
b101 %
b11100 '
1)
b010 *
b0000000001011011 +
0.
13
#797
03
#798
b0000000001011100 0
01
#799
b11100 #
b010 %
1,
13
#800
03
#801
#802
13
#803
03
#804
#805
13
#806
03
#807
12
#808
13
#809
03
#810
#811
13
#812
03
#813
#814
13
#815
03
#816
b0000000001011100 &
b101 *
1-
1.
b0000000001011100 /
11
#817
b101 %
b11101 '
0)
b0000000001011100 +
0-
b0000000000000000 /
13
#818
03
#819
b010 *
0.
b0000000001011101 0
01
02
#820
b11101 #
b010 %
0,
13
#821
03
#822
b0000000001011101 &
b101 *
1.
11
12
#823
b101 %
b11110 '
1)
b0000000001011101 +
1-
b0000000001011101 /
13
#824
03
#825
b0000000001011110 &
b0000000001011110 /
b0000000001011110 0
#826
b11110 #
b11111 '
0)
b0000000001011110 +
1,
0-
b0000000000000000 /
13
#827
03
#828
b010 *
0.
b0000000001011111 0
01
#829
b11111 #
b010 %
0,
13
#830
03
#831
b0000000001011111 &
b101 *
1.
11
02
#832
b101 %
b00000 '
b00011 (
b0000000001011111 +
13
#833
03
#834
b0000000001100000 &
b0000000001100000 0
#835
b00000 #
b00011 $
b00001 '
b0000000001100000 +
13
#836
03
#837
b0000000001100001 &
b0000000001100001 0
12
#838
b00001 #
b00010 '
b0000000001100001 +
13
#839
03
#840
b0000000001100010 &
b0000000001100010 0
02
#841
b00010 #
b00011 '
b0000000001100010 +
13
#842
03
#843
b010 *
0.
b0000000001100011 0
01
12
#844
b00011 #
b010 %
13
#845
03
#846
b0000000001100011 &
b101 *
1.
11
#847
b101 %
b00100 '
b0000000001100011 +
13
#848
03
#849
b0000000001100100 &
b0000000001100100 0
02
#850
b00100 #
b00101 '
b0000000001100100 +
13
#851
03
#852
b010 *
0.
b0000000001100101 0
01
#853
b00101 #
b010 %
13
#854
03
#855
#856
13
#857
03
#858
b0000000001100101 &
b101 *
1.
11
#859
b101 %
b00110 '
b0000000001100101 +
13
#860
03
#861
b010 *
0.
b0000000001100110 0
01
12
#862
b00110 #
b010 %
13
#863
03
#864
b0000000001100110 &
b101 *
1.
11
02
#865
b101 %
b00111 '
b0000000001100110 +
13
#866
03
#867
b010 *
0.
b0000000001100111 0
01
#868
b00111 #
b010 %
13
#869
03
#870
b0000000001100111 &
b101 *
1.
11
12
